<?xml version="1.0" encoding="utf-8"?><DEFECTS><DEFECT>
    <SFA>
      <FILEPATH>e:\work\modelling framework\modules\collision_algorithms\</FILEPATH>
      <FILENAME>collisionfunctions.cpp</FILENAME>
      <LINE>294</LINE>
      <COLUMN>7</COLUMN>
    </SFA>
    <DEFECTCODE>6246</DEFECTCODE>
    <DESCRIPTION>Local declaration of 'NewtonSeperation' hides declaration of the same name in outer scope. For additional information, see previous declaration at line '287' of 'e:\work\modelling framework\modules\collision_algorithms\collisionfunctions.cpp'.</DESCRIPTION>
    <FUNCTION>CollisionPair::CalculateMinimumSeparation</FUNCTION>
    <DECORATED>?CalculateMinimumSeparation@CollisionPair@@QEAANXZ</DECORATED>
    <FUNCLINE>277</FUNCLINE>
    <PATH>
      <SFA>
        <FILEPATH>e:\work\modelling framework\modules\collision_algorithms\</FILEPATH>
        <FILENAME>collisionfunctions.cpp</FILENAME>
        <LINE>287</LINE>
        <COLUMN>23</COLUMN>
      </SFA>
    </PATH>
  </DEFECT><DEFECT>
    <SFA>
      <FILEPATH>e:\work\modelling framework\modules\collision_algorithms\moid\</FILEPATH>
      <FILENAME>distlink.cpp</FILENAME>
      <LINE>1215</LINE>
      <COLUMN>40</COLUMN>
    </SFA>
    <DEFECTCODE>6001</DEFECTCODE>
    <DESCRIPTION>Using uninitialized memory 'delta'.</DESCRIPTION>
    <FUNCTION>MOID_direct_search</FUNCTION>
    <DECORATED>??$MOID_direct_search@M@@YA?AU?$SMOIDResult@M@@AEBV?$COrbitData@M@@0QEBIMM@Z</DECORATED>
    <FUNCLINE>1164</FUNCLINE>
    <PROBABILITY>1</PROBABILITY>
    <RANK>3</RANK>
    <CATEGORY>
      <RULECATEGORY>mspft</RULECATEGORY>
    </CATEGORY>
    <PATH>
      <SFA>
        <FILEPATH>e:\work\modelling framework\modules\collision_algorithms\moid\</FILEPATH>
        <FILENAME>distlink.cpp</FILENAME>
        <LINE>1168</LINE>
        <COLUMN>15</COLUMN>
      </SFA>
      <SFA>
        <FILEPATH>e:\work\modelling framework\modules\collision_algorithms\moid\</FILEPATH>
        <FILENAME>distlink.cpp</FILENAME>
        <LINE>1169</LINE>
        <COLUMN>21</COLUMN>
      </SFA>
      <SFA>
        <FILEPATH>e:\work\modelling framework\modules\collision_algorithms\moid\</FILEPATH>
        <FILENAME>distlink.cpp</FILENAME>
        <LINE>1170</LINE>
        <COLUMN>4</COLUMN>
      </SFA>
      <SFA>
        <FILEPATH>e:\work\modelling framework\modules\collision_algorithms\moid\</FILEPATH>
        <FILENAME>distlink.cpp</FILENAME>
        <LINE>1177</LINE>
        <COLUMN>18</COLUMN>
      </SFA>
      <SFA>
        <FILEPATH>e:\work\modelling framework\modules\collision_algorithms\moid\</FILEPATH>
        <FILENAME>distlink.cpp</FILENAME>
        <LINE>1178</LINE>
        <COLUMN>21</COLUMN>
      </SFA>
      <SFA>
        <FILEPATH>e:\work\modelling framework\modules\collision_algorithms\moid\</FILEPATH>
        <FILENAME>distlink.cpp</FILENAME>
        <LINE>1179</LINE>
        <COLUMN>5</COLUMN>
      </SFA>
      <SFA>
        <FILEPATH>e:\work\modelling framework\modules\collision_algorithms\moid\</FILEPATH>
        <FILENAME>distlink.cpp</FILENAME>
        <LINE>1180</LINE>
        <COLUMN>6</COLUMN>
      </SFA>
      <SFA>
        <FILEPATH>e:\work\modelling framework\modules\collision_algorithms\moid\</FILEPATH>
        <FILENAME>distlink.cpp</FILENAME>
        <LINE>1184</LINE>
        <COLUMN>22</COLUMN>
      </SFA>
      <SFA>
        <FILEPATH>e:\work\modelling framework\modules\collision_algorithms\moid\</FILEPATH>
        <FILENAME>distlink.cpp</FILENAME>
        <LINE>1185</LINE>
        <COLUMN>19</COLUMN>
      </SFA>
      <SFA>
        <FILEPATH>e:\work\modelling framework\modules\collision_algorithms\moid\</FILEPATH>
        <FILENAME>distlink.cpp</FILENAME>
        <LINE>1186</LINE>
        <COLUMN>6</COLUMN>
      </SFA>
      <SFA>
        <FILEPATH>e:\work\modelling framework\modules\collision_algorithms\moid\</FILEPATH>
        <FILENAME>distlink.cpp</FILENAME>
        <LINE>1187</LINE>
        <COLUMN>12</COLUMN>
      </SFA>
      <SFA>
        <FILEPATH>e:\work\modelling framework\modules\collision_algorithms\moid\</FILEPATH>
        <FILENAME>distlink.cpp</FILENAME>
        <LINE>1188</LINE>
        <COLUMN>9</COLUMN>
      </SFA>
      <SFA>
        <FILEPATH>e:\work\modelling framework\modules\collision_algorithms\moid\</FILEPATH>
        <FILENAME>distlink.cpp</FILENAME>
        <LINE>1188</LINE>
        <COLUMN>18</COLUMN>
      </SFA>
      <SFA>
        <FILEPATH>e:\work\modelling framework\modules\collision_algorithms\moid\</FILEPATH>
        <FILENAME>distlink.cpp</FILENAME>
        <LINE>1189</LINE>
        <COLUMN>10</COLUMN>
      </SFA>
      <SFA>
        <FILEPATH>e:\work\modelling framework\modules\collision_algorithms\moid\</FILEPATH>
        <FILENAME>distlink.cpp</FILENAME>
        <LINE>1189</LINE>
        <COLUMN>20</COLUMN>
      </SFA>
      <SFA>
        <FILEPATH>e:\work\modelling framework\modules\collision_algorithms\moid\</FILEPATH>
        <FILENAME>distlink.cpp</FILENAME>
        <LINE>1191</LINE>
        <COLUMN>10</COLUMN>
      </SFA>
      <SFA>
        <FILEPATH>e:\work\modelling framework\modules\collision_algorithms\moid\</FILEPATH>
        <FILENAME>distlink.cpp</FILENAME>
        <LINE>1191</LINE>
        <COLUMN>20</COLUMN>
      </SFA>
      <SFA>
        <FILEPATH>e:\work\modelling framework\modules\collision_algorithms\moid\</FILEPATH>
        <FILENAME>distlink.cpp</FILENAME>
        <LINE>1192</LINE>
        <COLUMN>11</COLUMN>
      </SFA>
      <SFA>
        <FILEPATH>e:\work\modelling framework\modules\collision_algorithms\moid\</FILEPATH>
        <FILENAME>distlink.cpp</FILENAME>
        <LINE>1191</LINE>
        <COLUMN>30</COLUMN>
      </SFA>
      <SFA>
        <FILEPATH>e:\work\modelling framework\modules\collision_algorithms\moid\</FILEPATH>
        <FILENAME>distlink.cpp</FILENAME>
        <LINE>1191</LINE>
        <COLUMN>20</COLUMN>
      </SFA>
      <SFA>
        <FILEPATH>e:\work\modelling framework\modules\collision_algorithms\moid\</FILEPATH>
        <FILENAME>distlink.cpp</FILENAME>
        <LINE>1193</LINE>
        <COLUMN>12</COLUMN>
      </SFA>
      <SFA>
        <FILEPATH>e:\work\modelling framework\modules\collision_algorithms\moid\</FILEPATH>
        <FILENAME>distlink.cpp</FILENAME>
        <LINE>1195</LINE>
        <COLUMN>7</COLUMN>
      </SFA>
      <SFA>
        <FILEPATH>e:\work\modelling framework\modules\collision_algorithms\moid\</FILEPATH>
        <FILENAME>distlink.cpp</FILENAME>
        <LINE>1196</LINE>
        <COLUMN>8</COLUMN>
      </SFA>
      <SFA>
        <FILEPATH>e:\work\modelling framework\modules\collision_algorithms\moid\</FILEPATH>
        <FILENAME>distlink.cpp</FILENAME>
        <LINE>1197</LINE>
        <COLUMN>8</COLUMN>
      </SFA>
      <SFA>
        <FILEPATH>e:\work\modelling framework\modules\collision_algorithms\moid\</FILEPATH>
        <FILENAME>distlink.cpp</FILENAME>
        <LINE>1198</LINE>
        <COLUMN>6</COLUMN>
      </SFA>
      <SFA>
        <FILEPATH>e:\work\modelling framework\modules\collision_algorithms\moid\</FILEPATH>
        <FILENAME>distlink.cpp</FILENAME>
        <LINE>1199</LINE>
        <COLUMN>10</COLUMN>
      </SFA>
      <SFA>
        <FILEPATH>e:\work\modelling framework\modules\collision_algorithms\moid\</FILEPATH>
        <FILENAME>distlink.cpp</FILENAME>
        <LINE>1203</LINE>
        <COLUMN>9</COLUMN>
      </SFA>
      <SFA>
        <FILEPATH>e:\work\modelling framework\modules\collision_algorithms\moid\</FILEPATH>
        <FILENAME>distlink.cpp</FILENAME>
        <LINE>1203</LINE>
        <COLUMN>19</COLUMN>
      </SFA>
      <SFA>
        <FILEPATH>e:\work\modelling framework\modules\collision_algorithms\moid\</FILEPATH>
        <FILENAME>distlink.cpp</FILENAME>
        <LINE>1205</LINE>
        <COLUMN>9</COLUMN>
      </SFA>
      <SFA>
        <FILEPATH>e:\work\modelling framework\modules\collision_algorithms\moid\</FILEPATH>
        <FILENAME>distlink.cpp</FILENAME>
        <LINE>1206</LINE>
        <COLUMN>9</COLUMN>
      </SFA>
      <SFA>
        <FILEPATH>e:\work\modelling framework\modules\collision_algorithms\moid\</FILEPATH>
        <FILENAME>distlink.cpp</FILENAME>
        <LINE>1207</LINE>
        <COLUMN>9</COLUMN>
      </SFA>
      <SFA>
        <FILEPATH>e:\work\modelling framework\modules\collision_algorithms\moid\</FILEPATH>
        <FILENAME>distlink.cpp</FILENAME>
        <LINE>1209</LINE>
        <COLUMN>6</COLUMN>
      </SFA>
      <SFA>
        <FILEPATH>e:\work\modelling framework\modules\collision_algorithms\moid\</FILEPATH>
        <FILENAME>distlink.cpp</FILENAME>
        <LINE>1211</LINE>
        <COLUMN>10</COLUMN>
      </SFA>
      <SFA>
        <FILEPATH>e:\work\modelling framework\modules\collision_algorithms\moid\</FILEPATH>
        <FILENAME>distlink.cpp</FILENAME>
        <LINE>1212</LINE>
        <COLUMN>10</COLUMN>
        <KEYEVENT>
          <ID>1</ID>
          <KIND>declaration</KIND>
          <IMPORTANCE>Essential</IMPORTANCE>
          <MESSAGE>'delta' is not initialized</MESSAGE>
        </KEYEVENT>
      </SFA>
      <SFA>
        <FILEPATH>e:\work\modelling framework\modules\collision_algorithms\moid\</FILEPATH>
        <FILENAME>distlink.cpp</FILENAME>
        <LINE>1213</LINE>
        <COLUMN>8</COLUMN>
      </SFA>
      <SFA>
        <FILEPATH>e:\work\modelling framework\modules\collision_algorithms\moid\</FILEPATH>
        <FILENAME>distlink.cpp</FILENAME>
        <LINE>1214</LINE>
        <COLUMN>16</COLUMN>
      </SFA>
      <SFA>
        <FILEPATH>e:\work\modelling framework\modules\collision_algorithms\moid\</FILEPATH>
        <FILENAME>distlink.cpp</FILENAME>
        <LINE>1215</LINE>
        <COLUMN>11</COLUMN>
      </SFA>
      <SFA>
        <FILEPATH>e:\work\modelling framework\modules\collision_algorithms\moid\</FILEPATH>
        <FILENAME>distlink.cpp</FILENAME>
        <LINE>1215</LINE>
        <COLUMN>40</COLUMN>
        <KEYEVENT>
          <ID>2</ID>
          <KIND>usage</KIND>
          <IMPORTANCE>Full</IMPORTANCE>
          <MESSAGE>'delta' is an Input to 'fabs' (declared at c:\program files (x86)\microsoft visual studio\2017\enterprise\vc\tools\msvc\14.10.25017\include\cmath:103)</MESSAGE>
        </KEYEVENT>
      </SFA>
      <SFA>
        <FILEPATH>e:\work\modelling framework\modules\collision_algorithms\moid\</FILEPATH>
        <FILENAME>distlink.cpp</FILENAME>
        <LINE>1215</LINE>
        <COLUMN>40</COLUMN>
        <KEYEVENT>
          <ID>3</ID>
          <KIND>branch</KIND>
          <IMPORTANCE>Full</IMPORTANCE>
          <MESSAGE>Enter this loop, (assume '&lt;branch condition&gt;')</MESSAGE>
        </KEYEVENT>
      </SFA>
      <SFA>
        <FILEPATH>e:\work\modelling framework\modules\collision_algorithms\moid\</FILEPATH>
        <FILENAME>distlink.cpp</FILENAME>
        <LINE>1217</LINE>
        <COLUMN>8</COLUMN>
        <KEYEVENT>
          <ID>4</ID>
          <KIND>branch</KIND>
          <IMPORTANCE>Full</IMPORTANCE>
          <MESSAGE>Skip this branch, (assume 'is_dens' is false)</MESSAGE>
        </KEYEVENT>
      </SFA>
      <SFA>
        <FILEPATH>e:\work\modelling framework\modules\collision_algorithms\moid\</FILEPATH>
        <FILENAME>distlink.cpp</FILENAME>
        <LINE>1220</LINE>
        <COLUMN>13</COLUMN>
      </SFA>
      <SFA>
        <FILEPATH>e:\work\modelling framework\modules\collision_algorithms\moid\</FILEPATH>
        <FILENAME>distlink.cpp</FILENAME>
        <LINE>1221</LINE>
        <COLUMN>7</COLUMN>
      </SFA>
      <SFA>
        <FILEPATH>e:\work\modelling framework\modules\collision_algorithms\moid\</FILEPATH>
        <FILENAME>distlink.cpp</FILENAME>
        <LINE>1222</LINE>
        <COLUMN>12</COLUMN>
      </SFA>
      <SFA>
        <FILEPATH>e:\work\modelling framework\modules\collision_algorithms\moid\</FILEPATH>
        <FILENAME>distlink.cpp</FILENAME>
        <LINE>1223</LINE>
        <COLUMN>7</COLUMN>
      </SFA>
      <SFA>
        <FILEPATH>e:\work\modelling framework\modules\collision_algorithms\moid\</FILEPATH>
        <FILENAME>distlink.cpp</FILENAME>
        <LINE>1224</LINE>
        <COLUMN>7</COLUMN>
      </SFA>
      <SFA>
        <FILEPATH>e:\work\modelling framework\modules\collision_algorithms\moid\</FILEPATH>
        <FILENAME>distlink.cpp</FILENAME>
        <LINE>1224</LINE>
        <COLUMN>16</COLUMN>
      </SFA>
      <SFA>
        <FILEPATH>e:\work\modelling framework\modules\collision_algorithms\moid\</FILEPATH>
        <FILENAME>distlink.cpp</FILENAME>
        <LINE>1225</LINE>
        <COLUMN>9</COLUMN>
        <KEYEVENT>
          <ID>5</ID>
          <KIND>branch</KIND>
          <IMPORTANCE>Full</IMPORTANCE>
          <MESSAGE>Skip this branch, (assume 'i&gt;0' is false)</MESSAGE>
        </KEYEVENT>
      </SFA>
      <SFA>
        <FILEPATH>e:\work\modelling framework\modules\collision_algorithms\moid\</FILEPATH>
        <FILENAME>distlink.cpp</FILENAME>
        <LINE>1226</LINE>
        <COLUMN>13</COLUMN>
      </SFA>
      <SFA>
        <FILEPATH>e:\work\modelling framework\modules\collision_algorithms\moid\</FILEPATH>
        <FILENAME>distlink.cpp</FILENAME>
        <LINE>1215</LINE>
        <COLUMN>72</COLUMN>
      </SFA>
      <SFA>
        <FILEPATH>e:\work\modelling framework\modules\collision_algorithms\moid\</FILEPATH>
        <FILENAME>distlink.cpp</FILENAME>
        <LINE>1215</LINE>
        <COLUMN>40</COLUMN>
        <KEYEVENT>
          <ID>6</ID>
          <KIND>usage</KIND>
          <IMPORTANCE>Full</IMPORTANCE>
          <MESSAGE>'delta' is an Input to 'fabs' (declared at c:\program files (x86)\microsoft visual studio\2017\enterprise\vc\tools\msvc\14.10.25017\include\cmath:103)</MESSAGE>
        </KEYEVENT>
      </SFA>
      <SFA>
        <FILEPATH>e:\work\modelling framework\modules\collision_algorithms\moid\</FILEPATH>
        <FILENAME>distlink.cpp</FILENAME>
        <LINE>1215</LINE>
        <COLUMN>40</COLUMN>
        <KEYEVENT>
          <ID>7</ID>
          <KIND>branch</KIND>
          <IMPORTANCE>Full</IMPORTANCE>
          <MESSAGE>Enter this loop, (assume '&lt;branch condition&gt;')</MESSAGE>
        </KEYEVENT>
      </SFA>
      <SFA>
        <FILEPATH>e:\work\modelling framework\modules\collision_algorithms\moid\</FILEPATH>
        <FILENAME>distlink.cpp</FILENAME>
        <LINE>1215</LINE>
        <COLUMN>40</COLUMN>
        <KEYEVENT>
          <ID>8</ID>
          <KIND>usage</KIND>
          <IMPORTANCE>Essential</IMPORTANCE>
          <MESSAGE>'delta' is used, but may not have been initialized</MESSAGE>
        </KEYEVENT>
      </SFA>
    </PATH>
  </DEFECT><DEFECT>
    <SFA>
      <FILEPATH>e:\work\modelling framework\modules\collision_algorithms\moid\</FILEPATH>
      <FILENAME>distlink.cpp</FILENAME>
      <LINE>568</LINE>
      <COLUMN>7</COLUMN>
    </SFA>
    <DEFECTCODE>6326</DEFECTCODE>
    <DESCRIPTION>Potential comparison of a constant with another constant.</DESCRIPTION>
    <FUNCTION>create_polynomial</FUNCTION>
    <DECORATED>??$create_polynomial@M@@YAMAEBU?$SAuxData@M@@QEAV?$complex@M@std@@@Z</DECORATED>
    <FUNCLINE>527</FUNCLINE>
    <PATH></PATH>
  </DEFECT><DEFECT>
    <SFA>
      <FILEPATH>e:\work\modelling framework\modules\collision_algorithms\moid\</FILEPATH>
      <FILENAME>distlink.cpp</FILENAME>
      <LINE>1120</LINE>
      <COLUMN>1</COLUMN>
    </SFA>
    <DEFECTCODE>6001</DEFECTCODE>
    <DESCRIPTION>Using uninitialized memory 'min_i'.</DESCRIPTION>
    <FUNCTION>search_in_segment</FUNCTION>
    <DECORATED>??$search_in_segment@M@@YAHAEBU?$SAuxData@M@@MMIAEAM@Z</DECORATED>
    <FUNCLINE>1107</FUNCLINE>
    <PROBABILITY>1</PROBABILITY>
    <RANK>3</RANK>
    <CATEGORY>
      <RULECATEGORY>mspft</RULECATEGORY>
    </CATEGORY>
    <PATH>
      <SFA>
        <FILEPATH>e:\work\modelling framework\modules\collision_algorithms\moid\</FILEPATH>
        <FILENAME>distlink.cpp</FILENAME>
        <LINE>1109</LINE>
        <COLUMN>9</COLUMN>
      </SFA>
      <SFA>
        <FILEPATH>e:\work\modelling framework\modules\collision_algorithms\moid\</FILEPATH>
        <FILENAME>distlink.cpp</FILENAME>
        <LINE>1110</LINE>
        <COLUMN>5</COLUMN>
        <KEYEVENT>
          <ID>1</ID>
          <KIND>declaration</KIND>
          <IMPORTANCE>Essential</IMPORTANCE>
          <MESSAGE>'min_i' is not initialized</MESSAGE>
        </KEYEVENT>
      </SFA>
      <SFA>
        <FILEPATH>e:\work\modelling framework\modules\collision_algorithms\moid\</FILEPATH>
        <FILENAME>distlink.cpp</FILENAME>
        <LINE>1111</LINE>
        <COLUMN>9</COLUMN>
      </SFA>
      <SFA>
        <FILEPATH>e:\work\modelling framework\modules\collision_algorithms\moid\</FILEPATH>
        <FILENAME>distlink.cpp</FILENAME>
        <LINE>1111</LINE>
        <COLUMN>15</COLUMN>
        <KEYEVENT>
          <ID>2</ID>
          <KIND>branch</KIND>
          <IMPORTANCE>Full</IMPORTANCE>
          <MESSAGE>Enter this loop, (assume 'i&lt;=N')</MESSAGE>
        </KEYEVENT>
      </SFA>
      <SFA>
        <FILEPATH>e:\work\modelling framework\modules\collision_algorithms\moid\</FILEPATH>
        <FILENAME>distlink.cpp</FILENAME>
        <LINE>1112</LINE>
        <COLUMN>16</COLUMN>
      </SFA>
      <SFA>
        <FILEPATH>e:\work\modelling framework\modules\collision_algorithms\moid\</FILEPATH>
        <FILENAME>distlink.cpp</FILENAME>
        <LINE>1113</LINE>
        <COLUMN>10</COLUMN>
      </SFA>
      <SFA>
        <FILEPATH>e:\work\modelling framework\modules\collision_algorithms\moid\</FILEPATH>
        <FILENAME>distlink.cpp</FILENAME>
        <LINE>1114</LINE>
        <COLUMN>16</COLUMN>
      </SFA>
      <SFA>
        <FILEPATH>e:\work\modelling framework\modules\collision_algorithms\moid\</FILEPATH>
        <FILENAME>distlink.cpp</FILENAME>
        <LINE>1115</LINE>
        <COLUMN>7</COLUMN>
        <KEYEVENT>
          <ID>3</ID>
          <KIND>branch</KIND>
          <IMPORTANCE>Full</IMPORTANCE>
          <MESSAGE>Enter this branch, (assume 'd&lt;0.000000')</MESSAGE>
        </KEYEVENT>
      </SFA>
      <SFA>
        <FILEPATH>e:\work\modelling framework\modules\collision_algorithms\moid\</FILEPATH>
        <FILENAME>distlink.cpp</FILENAME>
        <LINE>1111</LINE>
        <COLUMN>21</COLUMN>
      </SFA>
      <SFA>
        <FILEPATH>e:\work\modelling framework\modules\collision_algorithms\moid\</FILEPATH>
        <FILENAME>distlink.cpp</FILENAME>
        <LINE>1111</LINE>
        <COLUMN>15</COLUMN>
        <KEYEVENT>
          <ID>4</ID>
          <KIND>branch</KIND>
          <IMPORTANCE>Full</IMPORTANCE>
          <MESSAGE>Exit this loop, ('i&lt;=N' is false)</MESSAGE>
        </KEYEVENT>
      </SFA>
      <SFA>
        <FILEPATH>e:\work\modelling framework\modules\collision_algorithms\moid\</FILEPATH>
        <FILENAME>distlink.cpp</FILENAME>
        <LINE>1120</LINE>
        <COLUMN>1</COLUMN>
        <KEYEVENT>
          <ID>5</ID>
          <KIND>usage</KIND>
          <IMPORTANCE>Essential</IMPORTANCE>
          <MESSAGE>'min_i' is used, but may not have been initialized</MESSAGE>
        </KEYEVENT>
      </SFA>
    </PATH>
  </DEFECT><DEFECT>
    <SFA>
      <FILEPATH>e:\work\modelling framework\modules\collision_algorithms\moid\</FILEPATH>
      <FILENAME>moid.cpp</FILENAME>
      <LINE>259</LINE>
      <COLUMN>18</COLUMN>
    </SFA>
    <DEFECTCODE>6246</DEFECTCODE>
    <DESCRIPTION>Local declaration of 'dist_squared' hides declaration of the same name in outer scope. For additional information, see previous declaration at line '169' of 'e:\work\modelling framework\modules\collision_algorithms\moid\moid.cpp'.</DESCRIPTION>
    <FUNCTION>find_moid_full</FUNCTION>
    <DECORATED>?find_moid_full@@YANPEBUelements@@0PEAUmoid_data_t@@@Z</DECORATED>
    <FUNCLINE>162</FUNCLINE>
    <PATH>
      <SFA>
        <FILEPATH>e:\work\modelling framework\modules\collision_algorithms\moid\</FILEPATH>
        <FILENAME>moid.cpp</FILENAME>
        <LINE>169</LINE>
        <COLUMN>35</COLUMN>
      </SFA>
    </PATH>
  </DEFECT><DEFECT>
    <SFA>
      <FILEPATH>e:\work\modelling framework\modules\collision_algorithms\moid\</FILEPATH>
      <FILENAME>moid.cpp</FILENAME>
      <LINE>289</LINE>
      <COLUMN>22</COLUMN>
    </SFA>
    <DEFECTCODE>6011</DEFECTCODE>
    <DESCRIPTION>Dereferencing NULL pointer 'mdata'. </DESCRIPTION>
    <FUNCTION>find_moid_full</FUNCTION>
    <DECORATED>?find_moid_full@@YANPEBUelements@@0PEAUmoid_data_t@@@Z</DECORATED>
    <FUNCLINE>162</FUNCLINE>
    <PROBABILITY>1</PROBABILITY>
    <RANK>4</RANK>
    <CATEGORY>
      <RULECATEGORY>mspft</RULECATEGORY>
    </CATEGORY>
    <PATH>
      <SFA>
        <FILEPATH>e:\work\modelling framework\modules\collision_algorithms\moid\</FILEPATH>
        <FILENAME>moid.cpp</FILENAME>
        <LINE>164</LINE>
        <COLUMN>8</COLUMN>
      </SFA>
      <SFA>
        <FILEPATH>e:\work\modelling framework\modules\collision_algorithms\moid\</FILEPATH>
        <FILENAME>moid.cpp</FILENAME>
        <LINE>164</LINE>
        <COLUMN>20</COLUMN>
      </SFA>
      <SFA>
        <FILEPATH>e:\work\modelling framework\modules\collision_algorithms\moid\</FILEPATH>
        <FILENAME>moid.cpp</FILENAME>
        <LINE>165</LINE>
        <COLUMN>17</COLUMN>
      </SFA>
      <SFA>
        <FILEPATH>e:\work\modelling framework\modules\collision_algorithms\moid\</FILEPATH>
        <FILENAME>moid.cpp</FILENAME>
        <LINE>166</LINE>
        <COLUMN>13</COLUMN>
      </SFA>
      <SFA>
        <FILEPATH>e:\work\modelling framework\modules\collision_algorithms\moid\</FILEPATH>
        <FILENAME>moid.cpp</FILENAME>
        <LINE>167</LINE>
        <COLUMN>8</COLUMN>
      </SFA>
      <SFA>
        <FILEPATH>e:\work\modelling framework\modules\collision_algorithms\moid\</FILEPATH>
        <FILENAME>moid.cpp</FILENAME>
        <LINE>168</LINE>
        <COLUMN>5</COLUMN>
      </SFA>
      <SFA>
        <FILEPATH>e:\work\modelling framework\modules\collision_algorithms\moid\</FILEPATH>
        <FILENAME>moid.cpp</FILENAME>
        <LINE>168</LINE>
        <COLUMN>8</COLUMN>
      </SFA>
      <SFA>
        <FILEPATH>e:\work\modelling framework\modules\collision_algorithms\moid\</FILEPATH>
        <FILENAME>moid.cpp</FILENAME>
        <LINE>168</LINE>
        <COLUMN>11</COLUMN>
      </SFA>
      <SFA>
        <FILEPATH>e:\work\modelling framework\modules\collision_algorithms\moid\</FILEPATH>
        <FILENAME>moid.cpp</FILENAME>
        <LINE>168</LINE>
        <COLUMN>20</COLUMN>
      </SFA>
      <SFA>
        <FILEPATH>e:\work\modelling framework\modules\collision_algorithms\moid\</FILEPATH>
        <FILENAME>moid.cpp</FILENAME>
        <LINE>169</LINE>
        <COLUMN>8</COLUMN>
      </SFA>
      <SFA>
        <FILEPATH>e:\work\modelling framework\modules\collision_algorithms\moid\</FILEPATH>
        <FILENAME>moid.cpp</FILENAME>
        <LINE>169</LINE>
        <COLUMN>23</COLUMN>
      </SFA>
      <SFA>
        <FILEPATH>e:\work\modelling framework\modules\collision_algorithms\moid\</FILEPATH>
        <FILENAME>moid.cpp</FILENAME>
        <LINE>169</LINE>
        <COLUMN>37</COLUMN>
      </SFA>
      <SFA>
        <FILEPATH>e:\work\modelling framework\modules\collision_algorithms\moid\</FILEPATH>
        <FILENAME>moid.cpp</FILENAME>
        <LINE>170</LINE>
        <COLUMN>8</COLUMN>
      </SFA>
      <SFA>
        <FILEPATH>e:\work\modelling framework\modules\collision_algorithms\moid\</FILEPATH>
        <FILENAME>moid.cpp</FILENAME>
        <LINE>170</LINE>
        <COLUMN>28</COLUMN>
      </SFA>
      <SFA>
        <FILEPATH>e:\work\modelling framework\modules\collision_algorithms\moid\</FILEPATH>
        <FILENAME>moid.cpp</FILENAME>
        <LINE>170</LINE>
        <COLUMN>48</COLUMN>
      </SFA>
      <SFA>
        <FILEPATH>e:\work\modelling framework\modules\collision_algorithms\moid\</FILEPATH>
        <FILENAME>moid.cpp</FILENAME>
        <LINE>171</LINE>
        <COLUMN>14</COLUMN>
      </SFA>
      <SFA>
        <FILEPATH>e:\work\modelling framework\modules\collision_algorithms\moid\</FILEPATH>
        <FILENAME>moid.cpp</FILENAME>
        <LINE>172</LINE>
        <COLUMN>14</COLUMN>
      </SFA>
      <SFA>
        <FILEPATH>e:\work\modelling framework\modules\collision_algorithms\moid\</FILEPATH>
        <FILENAME>moid.cpp</FILENAME>
        <LINE>175</LINE>
        <COLUMN>12</COLUMN>
      </SFA>
      <SFA>
        <FILEPATH>e:\work\modelling framework\modules\collision_algorithms\moid\</FILEPATH>
        <FILENAME>moid.cpp</FILENAME>
        <LINE>176</LINE>
        <COLUMN>12</COLUMN>
      </SFA>
      <SFA>
        <FILEPATH>e:\work\modelling framework\modules\collision_algorithms\moid\</FILEPATH>
        <FILENAME>moid.cpp</FILENAME>
        <LINE>177</LINE>
        <COLUMN>8</COLUMN>
      </SFA>
      <SFA>
        <FILEPATH>e:\work\modelling framework\modules\collision_algorithms\moid\</FILEPATH>
        <FILENAME>moid.cpp</FILENAME>
        <LINE>177</LINE>
        <COLUMN>15</COLUMN>
      </SFA>
      <SFA>
        <FILEPATH>e:\work\modelling framework\modules\collision_algorithms\moid\</FILEPATH>
        <FILENAME>moid.cpp</FILENAME>
        <LINE>178</LINE>
        <COLUMN>9</COLUMN>
      </SFA>
      <SFA>
        <FILEPATH>e:\work\modelling framework\modules\collision_algorithms\moid\</FILEPATH>
        <FILENAME>moid.cpp</FILENAME>
        <LINE>178</LINE>
        <COLUMN>16</COLUMN>
      </SFA>
      <SFA>
        <FILEPATH>e:\work\modelling framework\modules\collision_algorithms\moid\</FILEPATH>
        <FILENAME>moid.cpp</FILENAME>
        <LINE>179</LINE>
        <COLUMN>28</COLUMN>
      </SFA>
      <SFA>
        <FILEPATH>e:\work\modelling framework\modules\collision_algorithms\moid\</FILEPATH>
        <FILENAME>moid.cpp</FILENAME>
        <LINE>178</LINE>
        <COLUMN>22</COLUMN>
      </SFA>
      <SFA>
        <FILEPATH>e:\work\modelling framework\modules\collision_algorithms\moid\</FILEPATH>
        <FILENAME>moid.cpp</FILENAME>
        <LINE>178</LINE>
        <COLUMN>16</COLUMN>
      </SFA>
      <SFA>
        <FILEPATH>e:\work\modelling framework\modules\collision_algorithms\moid\</FILEPATH>
        <FILENAME>moid.cpp</FILENAME>
        <LINE>179</LINE>
        <COLUMN>28</COLUMN>
      </SFA>
      <SFA>
        <FILEPATH>e:\work\modelling framework\modules\collision_algorithms\moid\</FILEPATH>
        <FILENAME>moid.cpp</FILENAME>
        <LINE>178</LINE>
        <COLUMN>22</COLUMN>
      </SFA>
      <SFA>
        <FILEPATH>e:\work\modelling framework\modules\collision_algorithms\moid\</FILEPATH>
        <FILENAME>moid.cpp</FILENAME>
        <LINE>178</LINE>
        <COLUMN>16</COLUMN>
      </SFA>
      <SFA>
        <FILEPATH>e:\work\modelling framework\modules\collision_algorithms\moid\</FILEPATH>
        <FILENAME>moid.cpp</FILENAME>
        <LINE>177</LINE>
        <COLUMN>21</COLUMN>
      </SFA>
      <SFA>
        <FILEPATH>e:\work\modelling framework\modules\collision_algorithms\moid\</FILEPATH>
        <FILENAME>moid.cpp</FILENAME>
        <LINE>177</LINE>
        <COLUMN>15</COLUMN>
      </SFA>
      <SFA>
        <FILEPATH>e:\work\modelling framework\modules\collision_algorithms\moid\</FILEPATH>
        <FILENAME>moid.cpp</FILENAME>
        <LINE>178</LINE>
        <COLUMN>9</COLUMN>
      </SFA>
      <SFA>
        <FILEPATH>e:\work\modelling framework\modules\collision_algorithms\moid\</FILEPATH>
        <FILENAME>moid.cpp</FILENAME>
        <LINE>178</LINE>
        <COLUMN>16</COLUMN>
      </SFA>
      <SFA>
        <FILEPATH>e:\work\modelling framework\modules\collision_algorithms\moid\</FILEPATH>
        <FILENAME>moid.cpp</FILENAME>
        <LINE>177</LINE>
        <COLUMN>21</COLUMN>
      </SFA>
      <SFA>
        <FILEPATH>e:\work\modelling framework\modules\collision_algorithms\moid\</FILEPATH>
        <FILENAME>moid.cpp</FILENAME>
        <LINE>177</LINE>
        <COLUMN>15</COLUMN>
      </SFA>
      <SFA>
        <FILEPATH>e:\work\modelling framework\modules\collision_algorithms\moid\</FILEPATH>
        <FILENAME>moid.cpp</FILENAME>
        <LINE>180</LINE>
        <COLUMN>13</COLUMN>
        <KEYEVENT>
          <ID>1</ID>
          <KIND>declaration</KIND>
          <IMPORTANCE>Essential</IMPORTANCE>
          <MESSAGE>'mdata' may be NULL</MESSAGE>
        </KEYEVENT>
      </SFA>
      <SFA>
        <FILEPATH>e:\work\modelling framework\modules\collision_algorithms\moid\</FILEPATH>
        <FILENAME>moid.cpp</FILENAME>
        <LINE>181</LINE>
        <COLUMN>26</COLUMN>
      </SFA>
      <SFA>
        <FILEPATH>e:\work\modelling framework\modules\collision_algorithms\moid\</FILEPATH>
        <FILENAME>moid.cpp</FILENAME>
        <LINE>182</LINE>
        <COLUMN>15</COLUMN>
      </SFA>
      <SFA>
        <FILEPATH>e:\work\modelling framework\modules\collision_algorithms\moid\</FILEPATH>
        <FILENAME>moid.cpp</FILENAME>
        <LINE>183</LINE>
        <COLUMN>13</COLUMN>
      </SFA>
      <SFA>
        <FILEPATH>e:\work\modelling framework\modules\collision_algorithms\moid\</FILEPATH>
        <FILENAME>moid.cpp</FILENAME>
        <LINE>184</LINE>
        <COLUMN>13</COLUMN>
      </SFA>
      <SFA>
        <FILEPATH>e:\work\modelling framework\modules\collision_algorithms\moid\</FILEPATH>
        <FILENAME>moid.cpp</FILENAME>
        <LINE>185</LINE>
        <COLUMN>15</COLUMN>
      </SFA>
      <SFA>
        <FILEPATH>e:\work\modelling framework\modules\collision_algorithms\moid\</FILEPATH>
        <FILENAME>moid.cpp</FILENAME>
        <LINE>187</LINE>
        <COLUMN>20</COLUMN>
      </SFA>
      <SFA>
        <FILEPATH>e:\work\modelling framework\modules\collision_algorithms\moid\</FILEPATH>
        <FILENAME>moid.cpp</FILENAME>
        <LINE>188</LINE>
        <COLUMN>19</COLUMN>
        <KEYEVENT>
          <ID>2</ID>
          <KIND>branch</KIND>
          <IMPORTANCE>Full</IMPORTANCE>
          <MESSAGE>Skip this branch, (assume '&lt;branch condition&gt;' is false)</MESSAGE>
        </KEYEVENT>
      </SFA>
      <SFA>
        <FILEPATH>e:\work\modelling framework\modules\collision_algorithms\moid\</FILEPATH>
        <FILENAME>moid.cpp</FILENAME>
        <LINE>194</LINE>
        <COLUMN>16</COLUMN>
        <KEYEVENT>
          <ID>3</ID>
          <KIND>branch</KIND>
          <IMPORTANCE>Full</IMPORTANCE>
          <MESSAGE>Skip this branch, (assume 'elem2-&gt;ecc&lt;1.000000' is false)</MESSAGE>
        </KEYEVENT>
      </SFA>
      <SFA>
        <FILEPATH>e:\work\modelling framework\modules\collision_algorithms\moid\</FILEPATH>
        <FILENAME>moid.cpp</FILENAME>
        <LINE>213</LINE>
        <COLUMN>11</COLUMN>
      </SFA>
      <SFA>
        <FILEPATH>e:\work\modelling framework\modules\collision_algorithms\moid\</FILEPATH>
        <FILENAME>moid.cpp</FILENAME>
        <LINE>213</LINE>
        <COLUMN>21</COLUMN>
        <KEYEVENT>
          <ID>4</ID>
          <KIND>branch</KIND>
          <IMPORTANCE>Full</IMPORTANCE>
          <MESSAGE>Enter this loop, (assume 'pass&lt;2')</MESSAGE>
        </KEYEVENT>
      </SFA>
      <SFA>
        <FILEPATH>e:\work\modelling framework\modules\collision_algorithms\moid\</FILEPATH>
        <FILENAME>moid.cpp</FILENAME>
        <LINE>215</LINE>
        <COLUMN>9</COLUMN>
      </SFA>
      <SFA>
        <FILEPATH>e:\work\modelling framework\modules\collision_algorithms\moid\</FILEPATH>
        <FILENAME>moid.cpp</FILENAME>
        <LINE>215</LINE>
        <COLUMN>15</COLUMN>
      </SFA>
      <SFA>
        <FILEPATH>e:\work\modelling framework\modules\collision_algorithms\moid\</FILEPATH>
        <FILENAME>moid.cpp</FILENAME>
        <LINE>217</LINE>
        <COLUMN>7</COLUMN>
      </SFA>
      <SFA>
        <FILEPATH>e:\work\modelling framework\modules\collision_algorithms\moid\</FILEPATH>
        <FILENAME>moid.cpp</FILENAME>
        <LINE>219</LINE>
        <COLUMN>23</COLUMN>
      </SFA>
      <SFA>
        <FILEPATH>e:\work\modelling framework\modules\collision_algorithms\moid\</FILEPATH>
        <FILENAME>moid.cpp</FILENAME>
        <LINE>221</LINE>
        <COLUMN>17</COLUMN>
      </SFA>
      <SFA>
        <FILEPATH>e:\work\modelling framework\modules\collision_algorithms\moid\</FILEPATH>
        <FILENAME>moid.cpp</FILENAME>
        <LINE>224</LINE>
        <COLUMN>15</COLUMN>
      </SFA>
      <SFA>
        <FILEPATH>e:\work\modelling framework\modules\collision_algorithms\moid\</FILEPATH>
        <FILENAME>moid.cpp</FILENAME>
        <LINE>229</LINE>
        <COLUMN>10</COLUMN>
      </SFA>
      <SFA>
        <FILEPATH>e:\work\modelling framework\modules\collision_algorithms\moid\</FILEPATH>
        <FILENAME>moid.cpp</FILENAME>
        <LINE>230</LINE>
        <COLUMN>9</COLUMN>
      </SFA>
      <SFA>
        <FILEPATH>e:\work\modelling framework\modules\collision_algorithms\moid\</FILEPATH>
        <FILENAME>moid.cpp</FILENAME>
        <LINE>230</LINE>
        <COLUMN>16</COLUMN>
      </SFA>
      <SFA>
        <FILEPATH>e:\work\modelling framework\modules\collision_algorithms\moid\</FILEPATH>
        <FILENAME>moid.cpp</FILENAME>
        <LINE>231</LINE>
        <COLUMN>8</COLUMN>
      </SFA>
      <SFA>
        <FILEPATH>e:\work\modelling framework\modules\collision_algorithms\moid\</FILEPATH>
        <FILENAME>moid.cpp</FILENAME>
        <LINE>230</LINE>
        <COLUMN>22</COLUMN>
      </SFA>
      <SFA>
        <FILEPATH>e:\work\modelling framework\modules\collision_algorithms\moid\</FILEPATH>
        <FILENAME>moid.cpp</FILENAME>
        <LINE>230</LINE>
        <COLUMN>16</COLUMN>
      </SFA>
      <SFA>
        <FILEPATH>e:\work\modelling framework\modules\collision_algorithms\moid\</FILEPATH>
        <FILENAME>moid.cpp</FILENAME>
        <LINE>231</LINE>
        <COLUMN>8</COLUMN>
      </SFA>
      <SFA>
        <FILEPATH>e:\work\modelling framework\modules\collision_algorithms\moid\</FILEPATH>
        <FILENAME>moid.cpp</FILENAME>
        <LINE>230</LINE>
        <COLUMN>22</COLUMN>
      </SFA>
      <SFA>
        <FILEPATH>e:\work\modelling framework\modules\collision_algorithms\moid\</FILEPATH>
        <FILENAME>moid.cpp</FILENAME>
        <LINE>230</LINE>
        <COLUMN>16</COLUMN>
      </SFA>
      <SFA>
        <FILEPATH>e:\work\modelling framework\modules\collision_algorithms\moid\</FILEPATH>
        <FILENAME>moid.cpp</FILENAME>
        <LINE>232</LINE>
        <COLUMN>9</COLUMN>
      </SFA>
      <SFA>
        <FILEPATH>e:\work\modelling framework\modules\collision_algorithms\moid\</FILEPATH>
        <FILENAME>moid.cpp</FILENAME>
        <LINE>232</LINE>
        <COLUMN>17</COLUMN>
        <KEYEVENT>
          <ID>5</ID>
          <KIND>branch</KIND>
          <IMPORTANCE>Full</IMPORTANCE>
          <MESSAGE>Skip this loop, (assume 'i&lt;=n_steps+1' is false)</MESSAGE>
        </KEYEVENT>
      </SFA>
      <SFA>
        <FILEPATH>e:\work\modelling framework\modules\collision_algorithms\moid\</FILEPATH>
        <FILENAME>moid.cpp</FILENAME>
        <LINE>213</LINE>
        <COLUMN>30</COLUMN>
      </SFA>
      <SFA>
        <FILEPATH>e:\work\modelling framework\modules\collision_algorithms\moid\</FILEPATH>
        <FILENAME>moid.cpp</FILENAME>
        <LINE>213</LINE>
        <COLUMN>21</COLUMN>
        <KEYEVENT>
          <ID>6</ID>
          <KIND>branch</KIND>
          <IMPORTANCE>Full</IMPORTANCE>
          <MESSAGE>Continue this loop, (assume 'pass&lt;2')</MESSAGE>
        </KEYEVENT>
      </SFA>
      <SFA>
        <FILEPATH>e:\work\modelling framework\modules\collision_algorithms\moid\</FILEPATH>
        <FILENAME>moid.cpp</FILENAME>
        <LINE>215</LINE>
        <COLUMN>9</COLUMN>
      </SFA>
      <SFA>
        <FILEPATH>e:\work\modelling framework\modules\collision_algorithms\moid\</FILEPATH>
        <FILENAME>moid.cpp</FILENAME>
        <LINE>215</LINE>
        <COLUMN>15</COLUMN>
      </SFA>
      <SFA>
        <FILEPATH>e:\work\modelling framework\modules\collision_algorithms\moid\</FILEPATH>
        <FILENAME>moid.cpp</FILENAME>
        <LINE>217</LINE>
        <COLUMN>7</COLUMN>
      </SFA>
      <SFA>
        <FILEPATH>e:\work\modelling framework\modules\collision_algorithms\moid\</FILEPATH>
        <FILENAME>moid.cpp</FILENAME>
        <LINE>219</LINE>
        <COLUMN>23</COLUMN>
      </SFA>
      <SFA>
        <FILEPATH>e:\work\modelling framework\modules\collision_algorithms\moid\</FILEPATH>
        <FILENAME>moid.cpp</FILENAME>
        <LINE>221</LINE>
        <COLUMN>17</COLUMN>
      </SFA>
      <SFA>
        <FILEPATH>e:\work\modelling framework\modules\collision_algorithms\moid\</FILEPATH>
        <FILENAME>moid.cpp</FILENAME>
        <LINE>224</LINE>
        <COLUMN>15</COLUMN>
      </SFA>
      <SFA>
        <FILEPATH>e:\work\modelling framework\modules\collision_algorithms\moid\</FILEPATH>
        <FILENAME>moid.cpp</FILENAME>
        <LINE>229</LINE>
        <COLUMN>10</COLUMN>
      </SFA>
      <SFA>
        <FILEPATH>e:\work\modelling framework\modules\collision_algorithms\moid\</FILEPATH>
        <FILENAME>moid.cpp</FILENAME>
        <LINE>230</LINE>
        <COLUMN>9</COLUMN>
      </SFA>
      <SFA>
        <FILEPATH>e:\work\modelling framework\modules\collision_algorithms\moid\</FILEPATH>
        <FILENAME>moid.cpp</FILENAME>
        <LINE>230</LINE>
        <COLUMN>16</COLUMN>
      </SFA>
      <SFA>
        <FILEPATH>e:\work\modelling framework\modules\collision_algorithms\moid\</FILEPATH>
        <FILENAME>moid.cpp</FILENAME>
        <LINE>232</LINE>
        <COLUMN>9</COLUMN>
      </SFA>
      <SFA>
        <FILEPATH>e:\work\modelling framework\modules\collision_algorithms\moid\</FILEPATH>
        <FILENAME>moid.cpp</FILENAME>
        <LINE>232</LINE>
        <COLUMN>17</COLUMN>
        <KEYEVENT>
          <ID>7</ID>
          <KIND>branch</KIND>
          <IMPORTANCE>Full</IMPORTANCE>
          <MESSAGE>Skip this loop, (assume 'i&lt;=n_steps+1' is false)</MESSAGE>
        </KEYEVENT>
      </SFA>
      <SFA>
        <FILEPATH>e:\work\modelling framework\modules\collision_algorithms\moid\</FILEPATH>
        <FILENAME>moid.cpp</FILENAME>
        <LINE>213</LINE>
        <COLUMN>30</COLUMN>
      </SFA>
      <SFA>
        <FILEPATH>e:\work\modelling framework\modules\collision_algorithms\moid\</FILEPATH>
        <FILENAME>moid.cpp</FILENAME>
        <LINE>213</LINE>
        <COLUMN>21</COLUMN>
        <KEYEVENT>
          <ID>8</ID>
          <KIND>branch</KIND>
          <IMPORTANCE>Full</IMPORTANCE>
          <MESSAGE>Exit this loop, ('pass&lt;2' is false)</MESSAGE>
        </KEYEVENT>
      </SFA>
      <SFA>
        <FILEPATH>e:\work\modelling framework\modules\collision_algorithms\moid\</FILEPATH>
        <FILENAME>moid.cpp</FILENAME>
        <LINE>273</LINE>
        <COLUMN>9</COLUMN>
      </SFA>
      <SFA>
        <FILEPATH>e:\work\modelling framework\modules\collision_algorithms\moid\</FILEPATH>
        <FILENAME>moid.cpp</FILENAME>
        <LINE>273</LINE>
        <COLUMN>19</COLUMN>
      </SFA>
      <SFA>
        <FILEPATH>e:\work\modelling framework\modules\collision_algorithms\moid\</FILEPATH>
        <FILENAME>moid.cpp</FILENAME>
        <LINE>273</LINE>
        <COLUMN>28</COLUMN>
      </SFA>
      <SFA>
        <FILEPATH>e:\work\modelling framework\modules\collision_algorithms\moid\</FILEPATH>
        <FILENAME>moid.cpp</FILENAME>
        <LINE>273</LINE>
        <COLUMN>37</COLUMN>
      </SFA>
      <SFA>
        <FILEPATH>e:\work\modelling framework\modules\collision_algorithms\moid\</FILEPATH>
        <FILENAME>moid.cpp</FILENAME>
        <LINE>273</LINE>
        <COLUMN>53</COLUMN>
      </SFA>
      <SFA>
        <FILEPATH>e:\work\modelling framework\modules\collision_algorithms\moid\</FILEPATH>
        <FILENAME>moid.cpp</FILENAME>
        <LINE>273</LINE>
        <COLUMN>63</COLUMN>
      </SFA>
      <SFA>
        <FILEPATH>e:\work\modelling framework\modules\collision_algorithms\moid\</FILEPATH>
        <FILENAME>moid.cpp</FILENAME>
        <LINE>275</LINE>
        <COLUMN>27</COLUMN>
      </SFA>
      <SFA>
        <FILEPATH>e:\work\modelling framework\modules\collision_algorithms\moid\</FILEPATH>
        <FILENAME>moid.cpp</FILENAME>
        <LINE>276</LINE>
        <COLUMN>19</COLUMN>
      </SFA>
      <SFA>
        <FILEPATH>e:\work\modelling framework\modules\collision_algorithms\moid\</FILEPATH>
        <FILENAME>moid.cpp</FILENAME>
        <LINE>277</LINE>
        <COLUMN>22</COLUMN>
      </SFA>
      <SFA>
        <FILEPATH>e:\work\modelling framework\modules\collision_algorithms\moid\</FILEPATH>
        <FILENAME>moid.cpp</FILENAME>
        <LINE>282</LINE>
        <COLUMN>22</COLUMN>
      </SFA>
      <SFA>
        <FILEPATH>e:\work\modelling framework\modules\collision_algorithms\moid\</FILEPATH>
        <FILENAME>moid.cpp</FILENAME>
        <LINE>287</LINE>
        <COLUMN>9</COLUMN>
      </SFA>
      <SFA>
        <FILEPATH>e:\work\modelling framework\modules\collision_algorithms\moid\</FILEPATH>
        <FILENAME>moid.cpp</FILENAME>
        <LINE>287</LINE>
        <COLUMN>16</COLUMN>
      </SFA>
      <SFA>
        <FILEPATH>e:\work\modelling framework\modules\collision_algorithms\moid\</FILEPATH>
        <FILENAME>moid.cpp</FILENAME>
        <LINE>288</LINE>
        <COLUMN>12</COLUMN>
      </SFA>
      <SFA>
        <FILEPATH>e:\work\modelling framework\modules\collision_algorithms\moid\</FILEPATH>
        <FILENAME>moid.cpp</FILENAME>
        <LINE>287</LINE>
        <COLUMN>22</COLUMN>
      </SFA>
      <SFA>
        <FILEPATH>e:\work\modelling framework\modules\collision_algorithms\moid\</FILEPATH>
        <FILENAME>moid.cpp</FILENAME>
        <LINE>287</LINE>
        <COLUMN>16</COLUMN>
      </SFA>
      <SFA>
        <FILEPATH>e:\work\modelling framework\modules\collision_algorithms\moid\</FILEPATH>
        <FILENAME>moid.cpp</FILENAME>
        <LINE>288</LINE>
        <COLUMN>12</COLUMN>
      </SFA>
      <SFA>
        <FILEPATH>e:\work\modelling framework\modules\collision_algorithms\moid\</FILEPATH>
        <FILENAME>moid.cpp</FILENAME>
        <LINE>287</LINE>
        <COLUMN>22</COLUMN>
      </SFA>
      <SFA>
        <FILEPATH>e:\work\modelling framework\modules\collision_algorithms\moid\</FILEPATH>
        <FILENAME>moid.cpp</FILENAME>
        <LINE>287</LINE>
        <COLUMN>16</COLUMN>
      </SFA>
      <SFA>
        <FILEPATH>e:\work\modelling framework\modules\collision_algorithms\moid\</FILEPATH>
        <FILENAME>moid.cpp</FILENAME>
        <LINE>289</LINE>
        <COLUMN>22</COLUMN>
        <KEYEVENT>
          <ID>9</ID>
          <KIND>usage</KIND>
          <IMPORTANCE>Essential</IMPORTANCE>
          <MESSAGE>'mdata' is dereferenced, but may still be NULL</MESSAGE>
        </KEYEVENT>
      </SFA>
    </PATH>
  </DEFECT><DEFECT>
    <SFA>
      <FILEPATH>e:\work\modelling framework\modules\collision_algorithms\</FILEPATH>
      <FILENAME>orbittrace.cpp</FILENAME>
      <LINE>217</LINE>
      <COLUMN>19</COLUMN>
    </SFA>
    <DEFECTCODE>6001</DEFECTCODE>
    <DESCRIPTION>Using uninitialized memory 'minSeperation'.</DESCRIPTION>
    <FUNCTION>OrbitTrace::CollisionRate</FUNCTION>
    <DECORATED>?CollisionRate@OrbitTrace@@MEAANAEAVCollisionPair@@@Z</DECORATED>
    <FUNCLINE>195</FUNCLINE>
    <PROBABILITY>1</PROBABILITY>
    <RANK>3</RANK>
    <CATEGORY>
      <RULECATEGORY>mspft</RULECATEGORY>
    </CATEGORY>
    <PATH>
      <SFA>
        <FILEPATH>e:\work\modelling framework\modules\collision_algorithms\</FILEPATH>
        <FILENAME>orbittrace.cpp</FILENAME>
        <LINE>197</LINE>
        <COLUMN>8</COLUMN>
      </SFA>
      <SFA>
        <FILEPATH>e:\work\modelling framework\modules\collision_algorithms\</FILEPATH>
        <FILENAME>orbittrace.cpp</FILENAME>
        <LINE>197</LINE>
        <COLUMN>23</COLUMN>
      </SFA>
      <SFA>
        <FILEPATH>e:\work\modelling framework\modules\collision_algorithms\</FILEPATH>
        <FILENAME>orbittrace.cpp</FILENAME>
        <LINE>197</LINE>
        <COLUMN>38</COLUMN>
        <KEYEVENT>
          <ID>1</ID>
          <KIND>declaration</KIND>
          <IMPORTANCE>Essential</IMPORTANCE>
          <MESSAGE>'minSeperation' is not initialized</MESSAGE>
        </KEYEVENT>
      </SFA>
      <SFA>
        <FILEPATH>e:\work\modelling framework\modules\collision_algorithms\</FILEPATH>
        <FILENAME>orbittrace.cpp</FILENAME>
        <LINE>197</LINE>
        <COLUMN>53</COLUMN>
      </SFA>
      <SFA>
        <FILEPATH>e:\work\modelling framework\modules\collision_algorithms\</FILEPATH>
        <FILENAME>orbittrace.cpp</FILENAME>
        <LINE>198</LINE>
        <COLUMN>10</COLUMN>
      </SFA>
      <SFA>
        <FILEPATH>e:\work\modelling framework\modules\collision_algorithms\</FILEPATH>
        <FILENAME>orbittrace.cpp</FILENAME>
        <LINE>198</LINE>
        <COLUMN>21</COLUMN>
      </SFA>
      <SFA>
        <FILEPATH>e:\work\modelling framework\modules\collision_algorithms\</FILEPATH>
        <FILENAME>orbittrace.cpp</FILENAME>
        <LINE>201</LINE>
        <COLUMN>9</COLUMN>
        <KEYEVENT>
          <ID>2</ID>
          <KIND>branch</KIND>
          <IMPORTANCE>Full</IMPORTANCE>
          <MESSAGE>Assume switch ( 'MOIDtype' ) resolves to the default case</MESSAGE>
        </KEYEVENT>
      </SFA>
      <SFA>
        <FILEPATH>e:\work\modelling framework\modules\collision_algorithms\</FILEPATH>
        <FILENAME>orbittrace.cpp</FILENAME>
        <LINE>208</LINE>
        <COLUMN>11</COLUMN>
      </SFA>
      <SFA>
        <FILEPATH>e:\work\modelling framework\modules\collision_algorithms\</FILEPATH>
        <FILENAME>orbittrace.cpp</FILENAME>
        <LINE>209</LINE>
        <COLUMN>11</COLUMN>
      </SFA>
      <SFA>
        <FILEPATH>e:\work\modelling framework\modules\collision_algorithms\</FILEPATH>
        <FILENAME>orbittrace.cpp</FILENAME>
        <LINE>211</LINE>
        <COLUMN>18</COLUMN>
      </SFA>
      <SFA>
        <FILEPATH>e:\work\modelling framework\modules\collision_algorithms\</FILEPATH>
        <FILENAME>orbittrace.cpp</FILENAME>
        <LINE>212</LINE>
        <COLUMN>15</COLUMN>
      </SFA>
      <SFA>
        <FILEPATH>e:\work\modelling framework\modules\collision_algorithms\</FILEPATH>
        <FILENAME>orbittrace.cpp</FILENAME>
        <LINE>213</LINE>
        <COLUMN>31</COLUMN>
      </SFA>
      <SFA>
        <FILEPATH>e:\work\modelling framework\modules\collision_algorithms\</FILEPATH>
        <FILENAME>orbittrace.cpp</FILENAME>
        <LINE>217</LINE>
        <COLUMN>19</COLUMN>
        <KEYEVENT>
          <ID>3</ID>
          <KIND>branch</KIND>
          <IMPORTANCE>Full</IMPORTANCE>
          <MESSAGE>Skip this branch, (assume 'boundingRadii&gt;minSeperation' is false)</MESSAGE>
        </KEYEVENT>
      </SFA>
      <SFA>
        <FILEPATH>e:\work\modelling framework\modules\collision_algorithms\</FILEPATH>
        <FILENAME>orbittrace.cpp</FILENAME>
        <LINE>217</LINE>
        <COLUMN>19</COLUMN>
        <KEYEVENT>
          <ID>4</ID>
          <KIND>usage</KIND>
          <IMPORTANCE>Essential</IMPORTANCE>
          <MESSAGE>'minSeperation' is used, but may not have been initialized</MESSAGE>
        </KEYEVENT>
      </SFA>
    </PATH>
  </DEFECT><DEFECT>
    <SFA>
      <FILEPATH>e:\work\modelling framework\modules\propagators\sgp4\sgp4code\</FILEPATH>
      <FILENAME>sgp4.cpp</FILENAME>
      <LINE>1953</LINE>
      <COLUMN>8</COLUMN>
    </SFA>
    <DEFECTCODE>6001</DEFECTCODE>
    <DESCRIPTION>Using uninitialized memory 'coseo1'.</DESCRIPTION>
    <FUNCTION>SGP4Funcs::sgp4</FUNCTION>
    <DECORATED>?sgp4@SGP4Funcs@@YA_NAEAUelsetrec@@NQEAN1@Z</DECORATED>
    <FUNCLINE>1740</FUNCLINE>
    <PROBABILITY>1</PROBABILITY>
    <RANK>3</RANK>
    <CATEGORY>
      <RULECATEGORY>mspft</RULECATEGORY>
    </CATEGORY>
    <PATH>
      <SFA>
        <FILEPATH>e:\work\modelling framework\modules\propagators\sgp4\sgp4code\</FILEPATH>
        <FILENAME>sgp4.cpp</FILENAME>
        <LINE>1745</LINE>
        <COLUMN>9</COLUMN>
      </SFA>
      <SFA>
        <FILEPATH>e:\work\modelling framework\modules\propagators\sgp4\sgp4code\</FILEPATH>
        <FILENAME>sgp4.cpp</FILENAME>
        <LINE>1745</LINE>
        <COLUMN>13</COLUMN>
      </SFA>
      <SFA>
        <FILEPATH>e:\work\modelling framework\modules\propagators\sgp4\sgp4code\</FILEPATH>
        <FILENAME>sgp4.cpp</FILENAME>
        <LINE>1745</LINE>
        <COLUMN>19</COLUMN>
      </SFA>
      <SFA>
        <FILEPATH>e:\work\modelling framework\modules\propagators\sgp4\sgp4code\</FILEPATH>
        <FILENAME>sgp4.cpp</FILENAME>
        <LINE>1745</LINE>
        <COLUMN>25</COLUMN>
      </SFA>
      <SFA>
        <FILEPATH>e:\work\modelling framework\modules\propagators\sgp4\sgp4code\</FILEPATH>
        <FILENAME>sgp4.cpp</FILENAME>
        <LINE>1745</LINE>
        <COLUMN>32</COLUMN>
      </SFA>
      <SFA>
        <FILEPATH>e:\work\modelling framework\modules\propagators\sgp4\sgp4code\</FILEPATH>
        <FILENAME>sgp4.cpp</FILENAME>
        <LINE>1745</LINE>
        <COLUMN>39</COLUMN>
      </SFA>
      <SFA>
        <FILEPATH>e:\work\modelling framework\modules\propagators\sgp4\sgp4code\</FILEPATH>
        <FILENAME>sgp4.cpp</FILENAME>
        <LINE>1746</LINE>
        <COLUMN>3</COLUMN>
      </SFA>
      <SFA>
        <FILEPATH>e:\work\modelling framework\modules\propagators\sgp4\sgp4code\</FILEPATH>
        <FILENAME>sgp4.cpp</FILENAME>
        <LINE>1746</LINE>
        <COLUMN>10</COLUMN>
        <KEYEVENT>
          <ID>1</ID>
          <KIND>declaration</KIND>
          <IMPORTANCE>Essential</IMPORTANCE>
          <MESSAGE>'coseo1' is not initialized</MESSAGE>
        </KEYEVENT>
      </SFA>
      <SFA>
        <FILEPATH>e:\work\modelling framework\modules\propagators\sgp4\sgp4code\</FILEPATH>
        <FILENAME>sgp4.cpp</FILENAME>
        <LINE>1746</LINE>
        <COLUMN>18</COLUMN>
      </SFA>
      <SFA>
        <FILEPATH>e:\work\modelling framework\modules\propagators\sgp4\sgp4code\</FILEPATH>
        <FILENAME>sgp4.cpp</FILENAME>
        <LINE>1746</LINE>
        <COLUMN>24</COLUMN>
      </SFA>
      <SFA>
        <FILEPATH>e:\work\modelling framework\modules\propagators\sgp4\sgp4code\</FILEPATH>
        <FILENAME>sgp4.cpp</FILENAME>
        <LINE>1746</LINE>
        <COLUMN>31</COLUMN>
      </SFA>
      <SFA>
        <FILEPATH>e:\work\modelling framework\modules\propagators\sgp4\sgp4code\</FILEPATH>
        <FILENAME>sgp4.cpp</FILENAME>
        <LINE>1746</LINE>
        <COLUMN>39</COLUMN>
      </SFA>
      <SFA>
        <FILEPATH>e:\work\modelling framework\modules\propagators\sgp4\sgp4code\</FILEPATH>
        <FILENAME>sgp4.cpp</FILENAME>
        <LINE>1746</LINE>
        <COLUMN>46</COLUMN>
      </SFA>
      <SFA>
        <FILEPATH>e:\work\modelling framework\modules\propagators\sgp4\sgp4code\</FILEPATH>
        <FILENAME>sgp4.cpp</FILENAME>
        <LINE>1747</LINE>
        <COLUMN>3</COLUMN>
      </SFA>
      <SFA>
        <FILEPATH>e:\work\modelling framework\modules\propagators\sgp4\sgp4code\</FILEPATH>
        <FILENAME>sgp4.cpp</FILENAME>
        <LINE>1747</LINE>
        <COLUMN>9</COLUMN>
      </SFA>
      <SFA>
        <FILEPATH>e:\work\modelling framework\modules\propagators\sgp4\sgp4code\</FILEPATH>
        <FILENAME>sgp4.cpp</FILENAME>
        <LINE>1747</LINE>
        <COLUMN>17</COLUMN>
      </SFA>
      <SFA>
        <FILEPATH>e:\work\modelling framework\modules\propagators\sgp4\sgp4code\</FILEPATH>
        <FILENAME>sgp4.cpp</FILENAME>
        <LINE>1747</LINE>
        <COLUMN>21</COLUMN>
      </SFA>
      <SFA>
        <FILEPATH>e:\work\modelling framework\modules\propagators\sgp4\sgp4code\</FILEPATH>
        <FILENAME>sgp4.cpp</FILENAME>
        <LINE>1747</LINE>
        <COLUMN>27</COLUMN>
      </SFA>
      <SFA>
        <FILEPATH>e:\work\modelling framework\modules\propagators\sgp4\sgp4code\</FILEPATH>
        <FILENAME>sgp4.cpp</FILENAME>
        <LINE>1747</LINE>
        <COLUMN>34</COLUMN>
      </SFA>
      <SFA>
        <FILEPATH>e:\work\modelling framework\modules\propagators\sgp4\sgp4code\</FILEPATH>
        <FILENAME>sgp4.cpp</FILENAME>
        <LINE>1747</LINE>
        <COLUMN>39</COLUMN>
      </SFA>
      <SFA>
        <FILEPATH>e:\work\modelling framework\modules\propagators\sgp4\sgp4code\</FILEPATH>
        <FILENAME>sgp4.cpp</FILENAME>
        <LINE>1748</LINE>
        <COLUMN>3</COLUMN>
      </SFA>
      <SFA>
        <FILEPATH>e:\work\modelling framework\modules\propagators\sgp4\sgp4code\</FILEPATH>
        <FILENAME>sgp4.cpp</FILENAME>
        <LINE>1748</LINE>
        <COLUMN>7</COLUMN>
      </SFA>
      <SFA>
        <FILEPATH>e:\work\modelling framework\modules\propagators\sgp4\sgp4code\</FILEPATH>
        <FILENAME>sgp4.cpp</FILENAME>
        <LINE>1748</LINE>
        <COLUMN>14</COLUMN>
      </SFA>
      <SFA>
        <FILEPATH>e:\work\modelling framework\modules\propagators\sgp4\sgp4code\</FILEPATH>
        <FILENAME>sgp4.cpp</FILENAME>
        <LINE>1748</LINE>
        <COLUMN>21</COLUMN>
      </SFA>
      <SFA>
        <FILEPATH>e:\work\modelling framework\modules\propagators\sgp4\sgp4code\</FILEPATH>
        <FILENAME>sgp4.cpp</FILENAME>
        <LINE>1748</LINE>
        <COLUMN>28</COLUMN>
      </SFA>
      <SFA>
        <FILEPATH>e:\work\modelling framework\modules\propagators\sgp4\sgp4code\</FILEPATH>
        <FILENAME>sgp4.cpp</FILENAME>
        <LINE>1748</LINE>
        <COLUMN>36</COLUMN>
      </SFA>
      <SFA>
        <FILEPATH>e:\work\modelling framework\modules\propagators\sgp4\sgp4code\</FILEPATH>
        <FILENAME>sgp4.cpp</FILENAME>
        <LINE>1748</LINE>
        <COLUMN>40</COLUMN>
      </SFA>
      <SFA>
        <FILEPATH>e:\work\modelling framework\modules\propagators\sgp4\sgp4code\</FILEPATH>
        <FILENAME>sgp4.cpp</FILENAME>
        <LINE>1749</LINE>
        <COLUMN>3</COLUMN>
      </SFA>
      <SFA>
        <FILEPATH>e:\work\modelling framework\modules\propagators\sgp4\sgp4code\</FILEPATH>
        <FILENAME>sgp4.cpp</FILENAME>
        <LINE>1749</LINE>
        <COLUMN>8</COLUMN>
      </SFA>
      <SFA>
        <FILEPATH>e:\work\modelling framework\modules\propagators\sgp4\sgp4code\</FILEPATH>
        <FILENAME>sgp4.cpp</FILENAME>
        <LINE>1749</LINE>
        <COLUMN>15</COLUMN>
      </SFA>
      <SFA>
        <FILEPATH>e:\work\modelling framework\modules\propagators\sgp4\sgp4code\</FILEPATH>
        <FILENAME>sgp4.cpp</FILENAME>
        <LINE>1749</LINE>
        <COLUMN>19</COLUMN>
      </SFA>
      <SFA>
        <FILEPATH>e:\work\modelling framework\modules\propagators\sgp4\sgp4code\</FILEPATH>
        <FILENAME>sgp4.cpp</FILENAME>
        <LINE>1749</LINE>
        <COLUMN>26</COLUMN>
      </SFA>
      <SFA>
        <FILEPATH>e:\work\modelling framework\modules\propagators\sgp4\sgp4code\</FILEPATH>
        <FILENAME>sgp4.cpp</FILENAME>
        <LINE>1749</LINE>
        <COLUMN>34</COLUMN>
      </SFA>
      <SFA>
        <FILEPATH>e:\work\modelling framework\modules\propagators\sgp4\sgp4code\</FILEPATH>
        <FILENAME>sgp4.cpp</FILENAME>
        <LINE>1750</LINE>
        <COLUMN>3</COLUMN>
      </SFA>
      <SFA>
        <FILEPATH>e:\work\modelling framework\modules\propagators\sgp4\sgp4code\</FILEPATH>
        <FILENAME>sgp4.cpp</FILENAME>
        <LINE>1750</LINE>
        <COLUMN>10</COLUMN>
      </SFA>
      <SFA>
        <FILEPATH>e:\work\modelling framework\modules\propagators\sgp4\sgp4code\</FILEPATH>
        <FILENAME>sgp4.cpp</FILENAME>
        <LINE>1750</LINE>
        <COLUMN>18</COLUMN>
      </SFA>
      <SFA>
        <FILEPATH>e:\work\modelling framework\modules\propagators\sgp4\sgp4code\</FILEPATH>
        <FILENAME>sgp4.cpp</FILENAME>
        <LINE>1750</LINE>
        <COLUMN>24</COLUMN>
      </SFA>
      <SFA>
        <FILEPATH>e:\work\modelling framework\modules\propagators\sgp4\sgp4code\</FILEPATH>
        <FILENAME>sgp4.cpp</FILENAME>
        <LINE>1750</LINE>
        <COLUMN>31</COLUMN>
      </SFA>
      <SFA>
        <FILEPATH>e:\work\modelling framework\modules\propagators\sgp4\sgp4code\</FILEPATH>
        <FILENAME>sgp4.cpp</FILENAME>
        <LINE>1750</LINE>
        <COLUMN>38</COLUMN>
      </SFA>
      <SFA>
        <FILEPATH>e:\work\modelling framework\modules\propagators\sgp4\sgp4code\</FILEPATH>
        <FILENAME>sgp4.cpp</FILENAME>
        <LINE>1751</LINE>
        <COLUMN>3</COLUMN>
      </SFA>
      <SFA>
        <FILEPATH>e:\work\modelling framework\modules\propagators\sgp4\sgp4code\</FILEPATH>
        <FILENAME>sgp4.cpp</FILENAME>
        <LINE>1751</LINE>
        <COLUMN>9</COLUMN>
      </SFA>
      <SFA>
        <FILEPATH>e:\work\modelling framework\modules\propagators\sgp4\sgp4code\</FILEPATH>
        <FILENAME>sgp4.cpp</FILENAME>
        <LINE>1751</LINE>
        <COLUMN>13</COLUMN>
      </SFA>
      <SFA>
        <FILEPATH>e:\work\modelling framework\modules\propagators\sgp4\sgp4code\</FILEPATH>
        <FILENAME>sgp4.cpp</FILENAME>
        <LINE>1751</LINE>
        <COLUMN>17</COLUMN>
      </SFA>
      <SFA>
        <FILEPATH>e:\work\modelling framework\modules\propagators\sgp4\sgp4code\</FILEPATH>
        <FILENAME>sgp4.cpp</FILENAME>
        <LINE>1751</LINE>
        <COLUMN>21</COLUMN>
      </SFA>
      <SFA>
        <FILEPATH>e:\work\modelling framework\modules\propagators\sgp4\sgp4code\</FILEPATH>
        <FILENAME>sgp4.cpp</FILENAME>
        <LINE>1751</LINE>
        <COLUMN>25</COLUMN>
      </SFA>
      <SFA>
        <FILEPATH>e:\work\modelling framework\modules\propagators\sgp4\sgp4code\</FILEPATH>
        <FILENAME>sgp4.cpp</FILENAME>
        <LINE>1751</LINE>
        <COLUMN>31</COLUMN>
      </SFA>
      <SFA>
        <FILEPATH>e:\work\modelling framework\modules\propagators\sgp4\sgp4code\</FILEPATH>
        <FILENAME>sgp4.cpp</FILENAME>
        <LINE>1752</LINE>
        <COLUMN>3</COLUMN>
      </SFA>
      <SFA>
        <FILEPATH>e:\work\modelling framework\modules\propagators\sgp4\sgp4code\</FILEPATH>
        <FILENAME>sgp4.cpp</FILENAME>
        <LINE>1752</LINE>
        <COLUMN>10</COLUMN>
      </SFA>
      <SFA>
        <FILEPATH>e:\work\modelling framework\modules\propagators\sgp4\sgp4code\</FILEPATH>
        <FILENAME>sgp4.cpp</FILENAME>
        <LINE>1752</LINE>
        <COLUMN>17</COLUMN>
      </SFA>
      <SFA>
        <FILEPATH>e:\work\modelling framework\modules\propagators\sgp4\sgp4code\</FILEPATH>
        <FILENAME>sgp4.cpp</FILENAME>
        <LINE>1752</LINE>
        <COLUMN>24</COLUMN>
      </SFA>
      <SFA>
        <FILEPATH>e:\work\modelling framework\modules\propagators\sgp4\sgp4code\</FILEPATH>
        <FILENAME>sgp4.cpp</FILENAME>
        <LINE>1752</LINE>
        <COLUMN>31</COLUMN>
      </SFA>
      <SFA>
        <FILEPATH>e:\work\modelling framework\modules\propagators\sgp4\sgp4code\</FILEPATH>
        <FILENAME>sgp4.cpp</FILENAME>
        <LINE>1752</LINE>
        <COLUMN>38</COLUMN>
      </SFA>
      <SFA>
        <FILEPATH>e:\work\modelling framework\modules\propagators\sgp4\sgp4code\</FILEPATH>
        <FILENAME>sgp4.cpp</FILENAME>
        <LINE>1752</LINE>
        <COLUMN>41</COLUMN>
      </SFA>
      <SFA>
        <FILEPATH>e:\work\modelling framework\modules\propagators\sgp4\sgp4code\</FILEPATH>
        <FILENAME>sgp4.cpp</FILENAME>
        <LINE>1753</LINE>
        <COLUMN>3</COLUMN>
      </SFA>
      <SFA>
        <FILEPATH>e:\work\modelling framework\modules\propagators\sgp4\sgp4code\</FILEPATH>
        <FILENAME>sgp4.cpp</FILENAME>
        <LINE>1753</LINE>
        <COLUMN>7</COLUMN>
      </SFA>
      <SFA>
        <FILEPATH>e:\work\modelling framework\modules\propagators\sgp4\sgp4code\</FILEPATH>
        <FILENAME>sgp4.cpp</FILENAME>
        <LINE>1753</LINE>
        <COLUMN>11</COLUMN>
      </SFA>
      <SFA>
        <FILEPATH>e:\work\modelling framework\modules\propagators\sgp4\sgp4code\</FILEPATH>
        <FILENAME>sgp4.cpp</FILENAME>
        <LINE>1753</LINE>
        <COLUMN>15</COLUMN>
      </SFA>
      <SFA>
        <FILEPATH>e:\work\modelling framework\modules\propagators\sgp4\sgp4code\</FILEPATH>
        <FILENAME>sgp4.cpp</FILENAME>
        <LINE>1753</LINE>
        <COLUMN>19</COLUMN>
      </SFA>
      <SFA>
        <FILEPATH>e:\work\modelling framework\modules\propagators\sgp4\sgp4code\</FILEPATH>
        <FILENAME>sgp4.cpp</FILENAME>
        <LINE>1753</LINE>
        <COLUMN>23</COLUMN>
      </SFA>
      <SFA>
        <FILEPATH>e:\work\modelling framework\modules\propagators\sgp4\sgp4code\</FILEPATH>
        <FILENAME>sgp4.cpp</FILENAME>
        <LINE>1753</LINE>
        <COLUMN>30</COLUMN>
      </SFA>
      <SFA>
        <FILEPATH>e:\work\modelling framework\modules\propagators\sgp4\sgp4code\</FILEPATH>
        <FILENAME>sgp4.cpp</FILENAME>
        <LINE>1754</LINE>
        <COLUMN>3</COLUMN>
      </SFA>
      <SFA>
        <FILEPATH>e:\work\modelling framework\modules\propagators\sgp4\sgp4code\</FILEPATH>
        <FILENAME>sgp4.cpp</FILENAME>
        <LINE>1754</LINE>
        <COLUMN>7</COLUMN>
      </SFA>
      <SFA>
        <FILEPATH>e:\work\modelling framework\modules\propagators\sgp4\sgp4code\</FILEPATH>
        <FILENAME>sgp4.cpp</FILENAME>
        <LINE>1754</LINE>
        <COLUMN>14</COLUMN>
      </SFA>
      <SFA>
        <FILEPATH>e:\work\modelling framework\modules\propagators\sgp4\sgp4code\</FILEPATH>
        <FILENAME>sgp4.cpp</FILENAME>
        <LINE>1754</LINE>
        <COLUMN>20</COLUMN>
      </SFA>
      <SFA>
        <FILEPATH>e:\work\modelling framework\modules\propagators\sgp4\sgp4code\</FILEPATH>
        <FILENAME>sgp4.cpp</FILENAME>
        <LINE>1754</LINE>
        <COLUMN>27</COLUMN>
      </SFA>
      <SFA>
        <FILEPATH>e:\work\modelling framework\modules\propagators\sgp4\sgp4code\</FILEPATH>
        <FILENAME>sgp4.cpp</FILENAME>
        <LINE>1754</LINE>
        <COLUMN>31</COLUMN>
      </SFA>
      <SFA>
        <FILEPATH>e:\work\modelling framework\modules\propagators\sgp4\sgp4code\</FILEPATH>
        <FILENAME>sgp4.cpp</FILENAME>
        <LINE>1754</LINE>
        <COLUMN>36</COLUMN>
      </SFA>
      <SFA>
        <FILEPATH>e:\work\modelling framework\modules\propagators\sgp4\sgp4code\</FILEPATH>
        <FILENAME>sgp4.cpp</FILENAME>
        <LINE>1755</LINE>
        <COLUMN>3</COLUMN>
      </SFA>
      <SFA>
        <FILEPATH>e:\work\modelling framework\modules\propagators\sgp4\sgp4code\</FILEPATH>
        <FILENAME>sgp4.cpp</FILENAME>
        <LINE>1755</LINE>
        <COLUMN>9</COLUMN>
      </SFA>
      <SFA>
        <FILEPATH>e:\work\modelling framework\modules\propagators\sgp4\sgp4code\</FILEPATH>
        <FILENAME>sgp4.cpp</FILENAME>
        <LINE>1755</LINE>
        <COLUMN>14</COLUMN>
      </SFA>
      <SFA>
        <FILEPATH>e:\work\modelling framework\modules\propagators\sgp4\sgp4code\</FILEPATH>
        <FILENAME>sgp4.cpp</FILENAME>
        <LINE>1755</LINE>
        <COLUMN>19</COLUMN>
      </SFA>
      <SFA>
        <FILEPATH>e:\work\modelling framework\modules\propagators\sgp4\sgp4code\</FILEPATH>
        <FILENAME>sgp4.cpp</FILENAME>
        <LINE>1755</LINE>
        <COLUMN>27</COLUMN>
      </SFA>
      <SFA>
        <FILEPATH>e:\work\modelling framework\modules\propagators\sgp4\sgp4code\</FILEPATH>
        <FILENAME>sgp4.cpp</FILENAME>
        <LINE>1755</LINE>
        <COLUMN>34</COLUMN>
      </SFA>
      <SFA>
        <FILEPATH>e:\work\modelling framework\modules\propagators\sgp4\sgp4code\</FILEPATH>
        <FILENAME>sgp4.cpp</FILENAME>
        <LINE>1755</LINE>
        <COLUMN>41</COLUMN>
      </SFA>
      <SFA>
        <FILEPATH>e:\work\modelling framework\modules\propagators\sgp4\sgp4code\</FILEPATH>
        <FILENAME>sgp4.cpp</FILENAME>
        <LINE>1755</LINE>
        <COLUMN>45</COLUMN>
      </SFA>
      <SFA>
        <FILEPATH>e:\work\modelling framework\modules\propagators\sgp4\sgp4code\</FILEPATH>
        <FILENAME>sgp4.cpp</FILENAME>
        <LINE>1756</LINE>
        <COLUMN>3</COLUMN>
      </SFA>
      <SFA>
        <FILEPATH>e:\work\modelling framework\modules\propagators\sgp4\sgp4code\</FILEPATH>
        <FILENAME>sgp4.cpp</FILENAME>
        <LINE>1756</LINE>
        <COLUMN>10</COLUMN>
      </SFA>
      <SFA>
        <FILEPATH>e:\work\modelling framework\modules\propagators\sgp4\sgp4code\</FILEPATH>
        <FILENAME>sgp4.cpp</FILENAME>
        <LINE>1756</LINE>
        <COLUMN>16</COLUMN>
      </SFA>
      <SFA>
        <FILEPATH>e:\work\modelling framework\modules\propagators\sgp4\sgp4code\</FILEPATH>
        <FILENAME>sgp4.cpp</FILENAME>
        <LINE>1756</LINE>
        <COLUMN>27</COLUMN>
      </SFA>
      <SFA>
        <FILEPATH>e:\work\modelling framework\modules\propagators\sgp4\sgp4code\</FILEPATH>
        <FILENAME>sgp4.cpp</FILENAME>
        <LINE>1757</LINE>
        <COLUMN>6</COLUMN>
      </SFA>
      <SFA>
        <FILEPATH>e:\work\modelling framework\modules\propagators\sgp4\sgp4code\</FILEPATH>
        <FILENAME>sgp4.cpp</FILENAME>
        <LINE>1763</LINE>
        <COLUMN>15</COLUMN>
      </SFA>
      <SFA>
        <FILEPATH>e:\work\modelling framework\modules\propagators\sgp4\sgp4code\</FILEPATH>
        <FILENAME>sgp4.cpp</FILENAME>
        <LINE>1764</LINE>
        <COLUMN>8</COLUMN>
      </SFA>
      <SFA>
        <FILEPATH>e:\work\modelling framework\modules\propagators\sgp4\sgp4code\</FILEPATH>
        <FILENAME>sgp4.cpp</FILENAME>
        <LINE>1765</LINE>
        <COLUMN>7</COLUMN>
      </SFA>
      <SFA>
        <FILEPATH>e:\work\modelling framework\modules\propagators\sgp4\sgp4code\</FILEPATH>
        <FILENAME>sgp4.cpp</FILENAME>
        <LINE>1768</LINE>
        <COLUMN>12</COLUMN>
      </SFA>
      <SFA>
        <FILEPATH>e:\work\modelling framework\modules\propagators\sgp4\sgp4code\</FILEPATH>
        <FILENAME>sgp4.cpp</FILENAME>
        <LINE>1771</LINE>
        <COLUMN>11</COLUMN>
      </SFA>
      <SFA>
        <FILEPATH>e:\work\modelling framework\modules\propagators\sgp4\sgp4code\</FILEPATH>
        <FILENAME>sgp4.cpp</FILENAME>
        <LINE>1772</LINE>
        <COLUMN>15</COLUMN>
      </SFA>
      <SFA>
        <FILEPATH>e:\work\modelling framework\modules\propagators\sgp4\sgp4code\</FILEPATH>
        <FILENAME>sgp4.cpp</FILENAME>
        <LINE>1775</LINE>
        <COLUMN>7</COLUMN>
      </SFA>
      <SFA>
        <FILEPATH>e:\work\modelling framework\modules\propagators\sgp4\sgp4code\</FILEPATH>
        <FILENAME>sgp4.cpp</FILENAME>
        <LINE>1776</LINE>
        <COLUMN>9</COLUMN>
      </SFA>
      <SFA>
        <FILEPATH>e:\work\modelling framework\modules\propagators\sgp4\sgp4code\</FILEPATH>
        <FILENAME>sgp4.cpp</FILENAME>
        <LINE>1777</LINE>
        <COLUMN>9</COLUMN>
      </SFA>
      <SFA>
        <FILEPATH>e:\work\modelling framework\modules\propagators\sgp4\sgp4code\</FILEPATH>
        <FILENAME>sgp4.cpp</FILENAME>
        <LINE>1778</LINE>
        <COLUMN>8</COLUMN>
      </SFA>
      <SFA>
        <FILEPATH>e:\work\modelling framework\modules\propagators\sgp4\sgp4code\</FILEPATH>
        <FILENAME>sgp4.cpp</FILENAME>
        <LINE>1779</LINE>
        <COLUMN>5</COLUMN>
      </SFA>
      <SFA>
        <FILEPATH>e:\work\modelling framework\modules\propagators\sgp4\sgp4code\</FILEPATH>
        <FILENAME>sgp4.cpp</FILENAME>
        <LINE>1780</LINE>
        <COLUMN>5</COLUMN>
      </SFA>
      <SFA>
        <FILEPATH>e:\work\modelling framework\modules\propagators\sgp4\sgp4code\</FILEPATH>
        <FILENAME>sgp4.cpp</FILENAME>
        <LINE>1781</LINE>
        <COLUMN>8</COLUMN>
      </SFA>
      <SFA>
        <FILEPATH>e:\work\modelling framework\modules\propagators\sgp4\sgp4code\</FILEPATH>
        <FILENAME>sgp4.cpp</FILENAME>
        <LINE>1782</LINE>
        <COLUMN>8</COLUMN>
      </SFA>
      <SFA>
        <FILEPATH>e:\work\modelling framework\modules\propagators\sgp4\sgp4code\</FILEPATH>
        <FILENAME>sgp4.cpp</FILENAME>
        <LINE>1783</LINE>
        <COLUMN>8</COLUMN>
      </SFA>
      <SFA>
        <FILEPATH>e:\work\modelling framework\modules\propagators\sgp4\sgp4code\</FILEPATH>
        <FILENAME>sgp4.cpp</FILENAME>
        <LINE>1784</LINE>
        <COLUMN>8</COLUMN>
      </SFA>
      <SFA>
        <FILEPATH>e:\work\modelling framework\modules\propagators\sgp4\sgp4code\</FILEPATH>
        <FILENAME>sgp4.cpp</FILENAME>
        <LINE>1786</LINE>
        <COLUMN>19</COLUMN>
      </SFA>
      <SFA>
        <FILEPATH>e:\work\modelling framework\modules\propagators\sgp4\sgp4code\</FILEPATH>
        <FILENAME>sgp4.cpp</FILENAME>
        <LINE>1807</LINE>
        <COLUMN>5</COLUMN>
      </SFA>
      <SFA>
        <FILEPATH>e:\work\modelling framework\modules\propagators\sgp4\sgp4code\</FILEPATH>
        <FILENAME>sgp4.cpp</FILENAME>
        <LINE>1808</LINE>
        <COLUMN>5</COLUMN>
      </SFA>
      <SFA>
        <FILEPATH>e:\work\modelling framework\modules\propagators\sgp4\sgp4code\</FILEPATH>
        <FILENAME>sgp4.cpp</FILENAME>
        <LINE>1809</LINE>
        <COLUMN>8</COLUMN>
      </SFA>
      <SFA>
        <FILEPATH>e:\work\modelling framework\modules\propagators\sgp4\sgp4code\</FILEPATH>
        <FILENAME>sgp4.cpp</FILENAME>
        <LINE>1810</LINE>
        <COLUMN>20</COLUMN>
      </SFA>
      <SFA>
        <FILEPATH>e:\work\modelling framework\modules\propagators\sgp4\sgp4code\</FILEPATH>
        <FILENAME>sgp4.cpp</FILENAME>
        <LINE>1830</LINE>
        <COLUMN>9</COLUMN>
        <KEYEVENT>
          <ID>2</ID>
          <KIND>branch</KIND>
          <IMPORTANCE>Full</IMPORTANCE>
          <MESSAGE>Skip this branch, (assume 'nm&lt;=0.000000' is false)</MESSAGE>
        </KEYEVENT>
      </SFA>
      <SFA>
        <FILEPATH>e:\work\modelling framework\modules\propagators\sgp4\sgp4code\</FILEPATH>
        <FILENAME>sgp4.cpp</FILENAME>
        <LINE>1837</LINE>
        <COLUMN>5</COLUMN>
      </SFA>
      <SFA>
        <FILEPATH>e:\work\modelling framework\modules\propagators\sgp4\sgp4code\</FILEPATH>
        <FILENAME>sgp4.cpp</FILENAME>
        <LINE>1838</LINE>
        <COLUMN>5</COLUMN>
      </SFA>
      <SFA>
        <FILEPATH>e:\work\modelling framework\modules\propagators\sgp4\sgp4code\</FILEPATH>
        <FILENAME>sgp4.cpp</FILENAME>
        <LINE>1839</LINE>
        <COLUMN>5</COLUMN>
      </SFA>
      <SFA>
        <FILEPATH>e:\work\modelling framework\modules\propagators\sgp4\sgp4code\</FILEPATH>
        <FILENAME>sgp4.cpp</FILENAME>
        <LINE>1843</LINE>
        <COLUMN>18</COLUMN>
        <KEYEVENT>
          <ID>3</ID>
          <KIND>branch</KIND>
          <IMPORTANCE>Full</IMPORTANCE>
          <MESSAGE>Skip this branch, (assume '&lt;branch condition&gt;' is false)</MESSAGE>
        </KEYEVENT>
      </SFA>
      <SFA>
        <FILEPATH>e:\work\modelling framework\modules\propagators\sgp4\sgp4code\</FILEPATH>
        <FILENAME>sgp4.cpp</FILENAME>
        <LINE>1851</LINE>
        <COLUMN>9</COLUMN>
        <KEYEVENT>
          <ID>4</ID>
          <KIND>branch</KIND>
          <IMPORTANCE>Full</IMPORTANCE>
          <MESSAGE>Skip this branch, (assume 'em&lt;0.000001' is false)</MESSAGE>
        </KEYEVENT>
      </SFA>
      <SFA>
        <FILEPATH>e:\work\modelling framework\modules\propagators\sgp4\sgp4code\</FILEPATH>
        <FILENAME>sgp4.cpp</FILENAME>
        <LINE>1853</LINE>
        <COLUMN>5</COLUMN>
      </SFA>
      <SFA>
        <FILEPATH>e:\work\modelling framework\modules\propagators\sgp4\sgp4code\</FILEPATH>
        <FILENAME>sgp4.cpp</FILENAME>
        <LINE>1854</LINE>
        <COLUMN>6</COLUMN>
      </SFA>
      <SFA>
        <FILEPATH>e:\work\modelling framework\modules\propagators\sgp4\sgp4code\</FILEPATH>
        <FILENAME>sgp4.cpp</FILENAME>
        <LINE>1855</LINE>
        <COLUMN>7</COLUMN>
      </SFA>
      <SFA>
        <FILEPATH>e:\work\modelling framework\modules\propagators\sgp4\sgp4code\</FILEPATH>
        <FILENAME>sgp4.cpp</FILENAME>
        <LINE>1856</LINE>
        <COLUMN>7</COLUMN>
      </SFA>
      <SFA>
        <FILEPATH>e:\work\modelling framework\modules\propagators\sgp4\sgp4code\</FILEPATH>
        <FILENAME>sgp4.cpp</FILENAME>
        <LINE>1858</LINE>
        <COLUMN>8</COLUMN>
      </SFA>
      <SFA>
        <FILEPATH>e:\work\modelling framework\modules\propagators\sgp4\sgp4code\</FILEPATH>
        <FILENAME>sgp4.cpp</FILENAME>
        <LINE>1859</LINE>
        <COLUMN>8</COLUMN>
      </SFA>
      <SFA>
        <FILEPATH>e:\work\modelling framework\modules\propagators\sgp4\sgp4code\</FILEPATH>
        <FILENAME>sgp4.cpp</FILENAME>
        <LINE>1860</LINE>
        <COLUMN>6</COLUMN>
      </SFA>
      <SFA>
        <FILEPATH>e:\work\modelling framework\modules\propagators\sgp4\sgp4code\</FILEPATH>
        <FILENAME>sgp4.cpp</FILENAME>
        <LINE>1861</LINE>
        <COLUMN>5</COLUMN>
      </SFA>
      <SFA>
        <FILEPATH>e:\work\modelling framework\modules\propagators\sgp4\sgp4code\</FILEPATH>
        <FILENAME>sgp4.cpp</FILENAME>
        <LINE>1864</LINE>
        <COLUMN>12</COLUMN>
      </SFA>
      <SFA>
        <FILEPATH>e:\work\modelling framework\modules\propagators\sgp4\sgp4code\</FILEPATH>
        <FILENAME>sgp4.cpp</FILENAME>
        <LINE>1865</LINE>
        <COLUMN>12</COLUMN>
      </SFA>
      <SFA>
        <FILEPATH>e:\work\modelling framework\modules\propagators\sgp4\sgp4code\</FILEPATH>
        <FILENAME>sgp4.cpp</FILENAME>
        <LINE>1866</LINE>
        <COLUMN>12</COLUMN>
      </SFA>
      <SFA>
        <FILEPATH>e:\work\modelling framework\modules\propagators\sgp4\sgp4code\</FILEPATH>
        <FILENAME>sgp4.cpp</FILENAME>
        <LINE>1867</LINE>
        <COLUMN>12</COLUMN>
      </SFA>
      <SFA>
        <FILEPATH>e:\work\modelling framework\modules\propagators\sgp4\sgp4code\</FILEPATH>
        <FILENAME>sgp4.cpp</FILENAME>
        <LINE>1868</LINE>
        <COLUMN>12</COLUMN>
      </SFA>
      <SFA>
        <FILEPATH>e:\work\modelling framework\modules\propagators\sgp4\sgp4code\</FILEPATH>
        <FILENAME>sgp4.cpp</FILENAME>
        <LINE>1869</LINE>
        <COLUMN>12</COLUMN>
      </SFA>
      <SFA>
        <FILEPATH>e:\work\modelling framework\modules\propagators\sgp4\sgp4code\</FILEPATH>
        <FILENAME>sgp4.cpp</FILENAME>
        <LINE>1870</LINE>
        <COLUMN>12</COLUMN>
      </SFA>
      <SFA>
        <FILEPATH>e:\work\modelling framework\modules\propagators\sgp4\sgp4code\</FILEPATH>
        <FILENAME>sgp4.cpp</FILENAME>
        <LINE>1873</LINE>
        <COLUMN>8</COLUMN>
      </SFA>
      <SFA>
        <FILEPATH>e:\work\modelling framework\modules\propagators\sgp4\sgp4code\</FILEPATH>
        <FILENAME>sgp4.cpp</FILENAME>
        <LINE>1874</LINE>
        <COLUMN>8</COLUMN>
      </SFA>
      <SFA>
        <FILEPATH>e:\work\modelling framework\modules\propagators\sgp4\sgp4code\</FILEPATH>
        <FILENAME>sgp4.cpp</FILENAME>
        <LINE>1877</LINE>
        <COLUMN>5</COLUMN>
      </SFA>
      <SFA>
        <FILEPATH>e:\work\modelling framework\modules\propagators\sgp4\sgp4code\</FILEPATH>
        <FILENAME>sgp4.cpp</FILENAME>
        <LINE>1878</LINE>
        <COLUMN>8</COLUMN>
      </SFA>
      <SFA>
        <FILEPATH>e:\work\modelling framework\modules\propagators\sgp4\sgp4code\</FILEPATH>
        <FILENAME>sgp4.cpp</FILENAME>
        <LINE>1879</LINE>
        <COLUMN>8</COLUMN>
      </SFA>
      <SFA>
        <FILEPATH>e:\work\modelling framework\modules\propagators\sgp4\sgp4code\</FILEPATH>
        <FILENAME>sgp4.cpp</FILENAME>
        <LINE>1880</LINE>
        <COLUMN>8</COLUMN>
      </SFA>
      <SFA>
        <FILEPATH>e:\work\modelling framework\modules\propagators\sgp4\sgp4code\</FILEPATH>
        <FILENAME>sgp4.cpp</FILENAME>
        <LINE>1881</LINE>
        <COLUMN>5</COLUMN>
      </SFA>
      <SFA>
        <FILEPATH>e:\work\modelling framework\modules\propagators\sgp4\sgp4code\</FILEPATH>
        <FILENAME>sgp4.cpp</FILENAME>
        <LINE>1882</LINE>
        <COLUMN>8</COLUMN>
      </SFA>
      <SFA>
        <FILEPATH>e:\work\modelling framework\modules\propagators\sgp4\sgp4code\</FILEPATH>
        <FILENAME>sgp4.cpp</FILENAME>
        <LINE>1883</LINE>
        <COLUMN>8</COLUMN>
      </SFA>
      <SFA>
        <FILEPATH>e:\work\modelling framework\modules\propagators\sgp4\sgp4code\</FILEPATH>
        <FILENAME>sgp4.cpp</FILENAME>
        <LINE>1884</LINE>
        <COLUMN>20</COLUMN>
        <KEYEVENT>
          <ID>5</ID>
          <KIND>branch</KIND>
          <IMPORTANCE>Full</IMPORTANCE>
          <MESSAGE>Skip this branch, (assume 'satrec.method==100' is false)</MESSAGE>
        </KEYEVENT>
      </SFA>
      <SFA>
        <FILEPATH>e:\work\modelling framework\modules\propagators\sgp4\sgp4code\</FILEPATH>
        <FILENAME>sgp4.cpp</FILENAME>
        <LINE>1917</LINE>
        <COLUMN>20</COLUMN>
      </SFA>
      <SFA>
        <FILEPATH>e:\work\modelling framework\modules\propagators\sgp4\sgp4code\</FILEPATH>
        <FILENAME>sgp4.cpp</FILENAME>
        <LINE>1928</LINE>
        <COLUMN>7</COLUMN>
      </SFA>
      <SFA>
        <FILEPATH>e:\work\modelling framework\modules\propagators\sgp4\sgp4code\</FILEPATH>
        <FILENAME>sgp4.cpp</FILENAME>
        <LINE>1929</LINE>
        <COLUMN>7</COLUMN>
      </SFA>
      <SFA>
        <FILEPATH>e:\work\modelling framework\modules\propagators\sgp4\sgp4code\</FILEPATH>
        <FILENAME>sgp4.cpp</FILENAME>
        <LINE>1930</LINE>
        <COLUMN>7</COLUMN>
      </SFA>
      <SFA>
        <FILEPATH>e:\work\modelling framework\modules\propagators\sgp4\sgp4code\</FILEPATH>
        <FILENAME>sgp4.cpp</FILENAME>
        <LINE>1931</LINE>
        <COLUMN>5</COLUMN>
      </SFA>
      <SFA>
        <FILEPATH>e:\work\modelling framework\modules\propagators\sgp4\sgp4code\</FILEPATH>
        <FILENAME>sgp4.cpp</FILENAME>
        <LINE>1934</LINE>
        <COLUMN>4</COLUMN>
      </SFA>
      <SFA>
        <FILEPATH>e:\work\modelling framework\modules\propagators\sgp4\sgp4code\</FILEPATH>
        <FILENAME>sgp4.cpp</FILENAME>
        <LINE>1935</LINE>
        <COLUMN>6</COLUMN>
      </SFA>
      <SFA>
        <FILEPATH>e:\work\modelling framework\modules\propagators\sgp4\sgp4code\</FILEPATH>
        <FILENAME>sgp4.cpp</FILENAME>
        <LINE>1936</LINE>
        <COLUMN>7</COLUMN>
      </SFA>
      <SFA>
        <FILEPATH>e:\work\modelling framework\modules\propagators\sgp4\sgp4code\</FILEPATH>
        <FILENAME>sgp4.cpp</FILENAME>
        <LINE>1937</LINE>
        <COLUMN>6</COLUMN>
      </SFA>
      <SFA>
        <FILEPATH>e:\work\modelling framework\modules\propagators\sgp4\sgp4code\</FILEPATH>
        <FILENAME>sgp4.cpp</FILENAME>
        <LINE>1940</LINE>
        <COLUMN>33</COLUMN>
        <KEYEVENT>
          <ID>6</ID>
          <KIND>branch</KIND>
          <IMPORTANCE>Full</IMPORTANCE>
          <MESSAGE>Skip this loop, (assume '&lt;branch condition&gt;' is false)</MESSAGE>
        </KEYEVENT>
      </SFA>
      <SFA>
        <FILEPATH>e:\work\modelling framework\modules\propagators\sgp4\sgp4code\</FILEPATH>
        <FILENAME>sgp4.cpp</FILENAME>
        <LINE>1953</LINE>
        <COLUMN>8</COLUMN>
        <KEYEVENT>
          <ID>7</ID>
          <KIND>usage</KIND>
          <IMPORTANCE>Essential</IMPORTANCE>
          <MESSAGE>'coseo1' is used, but may not have been initialized</MESSAGE>
        </KEYEVENT>
      </SFA>
    </PATH>
  </DEFECT><DEFECT>
    <SFA>
      <FILEPATH>e:\work\modelling framework\modules\propagators\sgp4\sgp4code\</FILEPATH>
      <FILENAME>sgp4.cpp</FILENAME>
      <LINE>2223</LINE>
      <COLUMN>10</COLUMN>
    </SFA>
    <DEFECTCODE>6328</DEFECTCODE>
    <DESCRIPTION>Size mismatch: 'unsigned __int64' passed as _Param_(6) when 'unsigned int' is required in call to 'sscanf_s'. </DESCRIPTION>
    <FUNCTION>SGP4Funcs::twoline2rv</FUNCTION>
    <DECORATED>?twoline2rv@SGP4Funcs@@YAXQEAD0DDDW4gravconsttype@@AEAN22AEAUelsetrec@@@Z</DECORATED>
    <FUNCLINE>2166</FUNCLINE>
    <PATH></PATH>
  </DEFECT><DEFECT>
    <SFA>
      <FILEPATH>e:\work\modelling framework\utilities\</FILEPATH>
      <FILENAME>baseutilities.cpp</FILENAME>
      <LINE>220</LINE>
      <COLUMN>9</COLUMN>
    </SFA>
    <DEFECTCODE>6246</DEFECTCODE>
    <DESCRIPTION>Local declaration of 'scenarioFilename' hides declaration of the same name in outer scope. For additional information, see previous declaration at line '145' of 'e:\work\modelling framework\utilities\baseutilities.cpp'.</DESCRIPTION>
    <FUNCTION>LoadScenario</FUNCTION>
    <DECORATED>?LoadScenario@@YAXAEAVDebrisPopulation@@V?$basic_string@DU?$char_traits@D@std@@V?$allocator@D@2@@std@@@Z</DECORATED>
    <FUNCLINE>145</FUNCLINE>
    <PATH>
      <SFA>
        <FILEPATH>e:\work\modelling framework\utilities\</FILEPATH>
        <FILENAME>baseutilities.cpp</FILENAME>
        <LINE>145</LINE>
        <COLUMN>72</COLUMN>
      </SFA>
    </PATH>
  </DEFECT><DEFECT>
    <SFA>
      <FILEPATH>e:\work\modelling framework\utilities\</FILEPATH>
      <FILENAME>orbitalutilities.cpp</FILENAME>
      <LINE>13</LINE>
      <COLUMN>12</COLUMN>
    </SFA>
    <DEFECTCODE>6244</DEFECTCODE>
    <DESCRIPTION>Local declaration of 'seed' hides previous declaration at line '6' of 'e:\work\modelling framework\utilities\orbitalutilities.cpp'.</DESCRIPTION>
    <FUNCTION>SeedRNG</FUNCTION>
    <DECORATED>?SeedRNG@@YAX_K@Z</DECORATED>
    <FUNCLINE>13</FUNCLINE>
    <PATH>
      <SFA>
        <FILEPATH>e:\work\modelling framework\utilities\</FILEPATH>
        <FILENAME>orbitalutilities.cpp</FILENAME>
        <LINE>6</LINE>
        <COLUMN>14</COLUMN>
      </SFA>
    </PATH>
  </DEFECT></DEFECTS>